{
  "meta": {
    "source": "NQ.c.0 (Nasdaq 100 futures, 2016-04-20\u20262024-12-31) + YM (E-mini Dow Jones, SMT partner)",
    "date_from": "2016-04-20",
    "date_to": "2024-12-31",
    "n_events_total": 48,
    "n_csv_events": 106,
    "generated_at": "2026-05-20T12:21:12.539251+00:00",
    "event_filter": "JOLTS",
    "csv": "/Users/angelo/news-cal-official/news_official_2016_2026.csv",
    "variants": {
      "no_be": "Pure SL/TP/timeout, no breakeven move",
      "be_50": "MFE>=50% TP-dist arms BE; bar touching entry exits flat",
      "tp1_be": "MFE>=50% closes half at +50% TP-dist AND moves stop to BE on remainder"
    },
    "smt": {
      "false": "no SMT filter",
      "true": "YM took its OPPOSITE-side pre-news liquidity (NQ short \u2192 YM low<pre_low; NQ long \u2192 YM high>pre_high)"
    },
    "tick": "NQ_TICK=0.25 (E-mini Nasdaq 100 futures)"
  },
  "rows": [
    {
      "year": "2016",
      "variant": "no_be",
      "smt": false,
      "side": "BOTH",
      "n": 4,
      "w": 1,
      "l": 3,
      "be": 0,
      "wr": 0.25,
      "pf": 1.178,
      "net_pts": 2.0,
      "avg_win": 13.25,
      "avg_loss": -3.75
    },
    {
      "year": "2017",
      "variant": "no_be",
      "smt": false,
      "side": "BOTH",
      "n": 4,
      "w": 2,
      "l": 2,
      "be": 0,
      "wr": 0.5,
      "pf": 1.0,
      "net_pts": 0.0,
      "avg_win": 4.0,
      "avg_loss": -4.0
    },
    {
      "year": "2018",
      "variant": "no_be",
      "smt": false,
      "side": "BOTH",
      "n": 3,
      "w": 3,
      "l": 0,
      "be": 0,
      "wr": 1.0,
      "pf": null,
      "net_pts": 43.25,
      "avg_win": 14.417,
      "avg_loss": 0.0
    },
    {
      "year": "2019",
      "variant": "no_be",
      "smt": false,
      "side": "BOTH",
      "n": 6,
      "w": 3,
      "l": 3,
      "be": 0,
      "wr": 0.5,
      "pf": 1.517,
      "net_pts": 11.5,
      "avg_win": 11.25,
      "avg_loss": -7.417
    },
    {
      "year": "2020",
      "variant": "no_be",
      "smt": false,
      "side": "BOTH",
      "n": 7,
      "w": 0,
      "l": 7,
      "be": 0,
      "wr": 0.0,
      "pf": 0.0,
      "net_pts": -168.25,
      "avg_win": 0.0,
      "avg_loss": -24.036
    },
    {
      "year": "2021",
      "variant": "no_be",
      "smt": false,
      "side": "BOTH",
      "n": 5,
      "w": 3,
      "l": 2,
      "be": 0,
      "wr": 0.6,
      "pf": 1.029,
      "net_pts": 1.25,
      "avg_win": 14.917,
      "avg_loss": -21.75
    },
    {
      "year": "2022",
      "variant": "no_be",
      "smt": false,
      "side": "BOTH",
      "n": 5,
      "w": 0,
      "l": 5,
      "be": 0,
      "wr": 0.0,
      "pf": 0.0,
      "net_pts": -179.0,
      "avg_win": 0.0,
      "avg_loss": -35.8
    },
    {
      "year": "2023",
      "variant": "no_be",
      "smt": false,
      "side": "BOTH",
      "n": 7,
      "w": 2,
      "l": 5,
      "be": 0,
      "wr": 0.2857,
      "pf": 0.309,
      "net_pts": -100.5,
      "avg_win": 22.5,
      "avg_loss": -29.1
    },
    {
      "year": "2024",
      "variant": "no_be",
      "smt": false,
      "side": "BOTH",
      "n": 7,
      "w": 3,
      "l": 4,
      "be": 0,
      "wr": 0.4286,
      "pf": 0.638,
      "net_pts": -54.0,
      "avg_win": 31.667,
      "avg_loss": -37.25
    },
    {
      "year": "ALL",
      "variant": "no_be",
      "smt": false,
      "side": "BOTH",
      "n": 48,
      "w": 17,
      "l": 31,
      "be": 0,
      "wr": 0.3542,
      "pf": 0.389,
      "net_pts": -443.75,
      "avg_win": 16.647,
      "avg_loss": -23.444
    },
    {
      "year": "2016",
      "variant": "no_be",
      "smt": false,
      "side": "LONG",
      "n": 1,
      "w": 1,
      "l": 0,
      "be": 0,
      "wr": 1.0,
      "pf": null,
      "net_pts": 13.25,
      "avg_win": 13.25,
      "avg_loss": 0.0
    },
    {
      "year": "2017",
      "variant": "no_be",
      "smt": false,
      "side": "LONG",
      "n": 1,
      "w": 1,
      "l": 0,
      "be": 0,
      "wr": 1.0,
      "pf": null,
      "net_pts": 5.0,
      "avg_win": 5.0,
      "avg_loss": 0.0
    },
    {
      "year": "2018",
      "variant": "no_be",
      "smt": false,
      "side": "LONG",
      "n": 1,
      "w": 1,
      "l": 0,
      "be": 0,
      "wr": 1.0,
      "pf": null,
      "net_pts": 5.25,
      "avg_win": 5.25,
      "avg_loss": 0.0
    },
    {
      "year": "2019",
      "variant": "no_be",
      "smt": false,
      "side": "LONG",
      "n": 1,
      "w": 1,
      "l": 0,
      "be": 0,
      "wr": 1.0,
      "pf": null,
      "net_pts": 17.25,
      "avg_win": 17.25,
      "avg_loss": 0.0
    },
    {
      "year": "2020",
      "variant": "no_be",
      "smt": false,
      "side": "LONG",
      "n": 3,
      "w": 0,
      "l": 3,
      "be": 0,
      "wr": 0.0,
      "pf": 0.0,
      "net_pts": -78.0,
      "avg_win": 0.0,
      "avg_loss": -26.0
    },
    {
      "year": "2021",
      "variant": "no_be",
      "smt": false,
      "side": "LONG",
      "n": 2,
      "w": 2,
      "l": 0,
      "be": 0,
      "wr": 1.0,
      "pf": null,
      "net_pts": 27.75,
      "avg_win": 13.875,
      "avg_loss": 0.0
    },
    {
      "year": "2022",
      "variant": "no_be",
      "smt": false,
      "side": "LONG",
      "n": 3,
      "w": 0,
      "l": 3,
      "be": 0,
      "wr": 0.0,
      "pf": 0.0,
      "net_pts": -117.75,
      "avg_win": 0.0,
      "avg_loss": -39.25
    },
    {
      "year": "2023",
      "variant": "no_be",
      "smt": false,
      "side": "LONG",
      "n": 4,
      "w": 1,
      "l": 3,
      "be": 0,
      "wr": 0.25,
      "pf": 0.248,
      "net_pts": -57.5,
      "avg_win": 19.0,
      "avg_loss": -25.5
    },
    {
      "year": "2024",
      "variant": "no_be",
      "smt": false,
      "side": "LONG",
      "n": 4,
      "w": 1,
      "l": 3,
      "be": 0,
      "wr": 0.25,
      "pf": 0.538,
      "net_pts": -40.5,
      "avg_win": 47.25,
      "avg_loss": -29.25
    },
    {
      "year": "ALL",
      "variant": "no_be",
      "smt": false,
      "side": "LONG",
      "n": 20,
      "w": 8,
      "l": 12,
      "be": 0,
      "wr": 0.4,
      "pf": 0.374,
      "net_pts": -225.25,
      "avg_win": 16.844,
      "avg_loss": -30.0
    },
    {
      "year": "2016",
      "variant": "no_be",
      "smt": false,
      "side": "SHORT",
      "n": 3,
      "w": 0,
      "l": 3,
      "be": 0,
      "wr": 0.0,
      "pf": 0.0,
      "net_pts": -11.25,
      "avg_win": 0.0,
      "avg_loss": -3.75
    },
    {
      "year": "2017",
      "variant": "no_be",
      "smt": false,
      "side": "SHORT",
      "n": 3,
      "w": 1,
      "l": 2,
      "be": 0,
      "wr": 0.3333,
      "pf": 0.375,
      "net_pts": -5.0,
      "avg_win": 3.0,
      "avg_loss": -4.0
    },
    {
      "year": "2018",
      "variant": "no_be",
      "smt": false,
      "side": "SHORT",
      "n": 2,
      "w": 2,
      "l": 0,
      "be": 0,
      "wr": 1.0,
      "pf": null,
      "net_pts": 38.0,
      "avg_win": 19.0,
      "avg_loss": 0.0
    },
    {
      "year": "2019",
      "variant": "no_be",
      "smt": false,
      "side": "SHORT",
      "n": 5,
      "w": 2,
      "l": 3,
      "be": 0,
      "wr": 0.4,
      "pf": 0.742,
      "net_pts": -5.75,
      "avg_win": 8.25,
      "avg_loss": -7.417
    },
    {
      "year": "2020",
      "variant": "no_be",
      "smt": false,
      "side": "SHORT",
      "n": 4,
      "w": 0,
      "l": 4,
      "be": 0,
      "wr": 0.0,
      "pf": 0.0,
      "net_pts": -90.25,
      "avg_win": 0.0,
      "avg_loss": -22.562
    },
    {
      "year": "2021",
      "variant": "no_be",
      "smt": false,
      "side": "SHORT",
      "n": 3,
      "w": 1,
      "l": 2,
      "be": 0,
      "wr": 0.3333,
      "pf": 0.391,
      "net_pts": -26.5,
      "avg_win": 17.0,
      "avg_loss": -21.75
    },
    {
      "year": "2022",
      "variant": "no_be",
      "smt": false,
      "side": "SHORT",
      "n": 2,
      "w": 0,
      "l": 2,
      "be": 0,
      "wr": 0.0,
      "pf": 0.0,
      "net_pts": -61.25,
      "avg_win": 0.0,
      "avg_loss": -30.625
    },
    {
      "year": "2023",
      "variant": "no_be",
      "smt": false,
      "side": "SHORT",
      "n": 3,
      "w": 1,
      "l": 2,
      "be": 0,
      "wr": 0.3333,
      "pf": 0.377,
      "net_pts": -43.0,
      "avg_win": 26.0,
      "avg_loss": -34.5
    },
    {
      "year": "2024",
      "variant": "no_be",
      "smt": false,
      "side": "SHORT",
      "n": 3,
      "w": 2,
      "l": 1,
      "be": 0,
      "wr": 0.6667,
      "pf": 0.78,
      "net_pts": -13.5,
      "avg_win": 23.875,
      "avg_loss": -61.25
    },
    {
      "year": "ALL",
      "variant": "no_be",
      "smt": false,
      "side": "SHORT",
      "n": 28,
      "w": 9,
      "l": 19,
      "be": 0,
      "wr": 0.3214,
      "pf": 0.404,
      "net_pts": -218.5,
      "avg_win": 16.472,
      "avg_loss": -19.303
    },
    {
      "year": "2016",
      "variant": "no_be",
      "smt": true,
      "side": "BOTH",
      "n": 1,
      "w": 0,
      "l": 1,
      "be": 0,
      "wr": 0.0,
      "pf": 0.0,
      "net_pts": -4.0,
      "avg_win": 0.0,
      "avg_loss": -4.0
    },
    {
      "year": "2017",
      "variant": "no_be",
      "smt": true,
      "side": "BOTH",
      "n": 4,
      "w": 2,
      "l": 2,
      "be": 0,
      "wr": 0.5,
      "pf": 1.0,
      "net_pts": 0.0,
      "avg_win": 4.0,
      "avg_loss": -4.0
    },
    {
      "year": "2018",
      "variant": "no_be",
      "smt": true,
      "side": "BOTH",
      "n": 3,
      "w": 3,
      "l": 0,
      "be": 0,
      "wr": 1.0,
      "pf": null,
      "net_pts": 43.25,
      "avg_win": 14.417,
      "avg_loss": 0.0
    },
    {
      "year": "2019",
      "variant": "no_be",
      "smt": true,
      "side": "BOTH",
      "n": 4,
      "w": 2,
      "l": 2,
      "be": 0,
      "wr": 0.5,
      "pf": 0.985,
      "net_pts": -0.25,
      "avg_win": 8.25,
      "avg_loss": -8.375
    },
    {
      "year": "2020",
      "variant": "no_be",
      "smt": true,
      "side": "BOTH",
      "n": 4,
      "w": 0,
      "l": 4,
      "be": 0,
      "wr": 0.0,
      "pf": 0.0,
      "net_pts": -52.5,
      "avg_win": 0.0,
      "avg_loss": -13.125
    },
    {
      "year": "2021",
      "variant": "no_be",
      "smt": true,
      "side": "BOTH",
      "n": 5,
      "w": 3,
      "l": 2,
      "be": 0,
      "wr": 0.6,
      "pf": 1.029,
      "net_pts": 1.25,
      "avg_win": 14.917,
      "avg_loss": -21.75
    },
    {
      "year": "2022",
      "variant": "no_be",
      "smt": true,
      "side": "BOTH",
      "n": 2,
      "w": 0,
      "l": 2,
      "be": 0,
      "wr": 0.0,
      "pf": 0.0,
      "net_pts": -43.0,
      "avg_win": 0.0,
      "avg_loss": -21.5
    },
    {
      "year": "2023",
      "variant": "no_be",
      "smt": true,
      "side": "BOTH",
      "n": 3,
      "w": 1,
      "l": 2,
      "be": 0,
      "wr": 0.3333,
      "pf": 0.377,
      "net_pts": -43.0,
      "avg_win": 26.0,
      "avg_loss": -34.5
    },
    {
      "year": "2024",
      "variant": "no_be",
      "smt": true,
      "side": "BOTH",
      "n": 4,
      "w": 2,
      "l": 2,
      "be": 0,
      "wr": 0.5,
      "pf": 0.786,
      "net_pts": -17.0,
      "avg_win": 31.25,
      "avg_loss": -39.75
    },
    {
      "year": "ALL",
      "variant": "no_be",
      "smt": true,
      "side": "BOTH",
      "n": 30,
      "w": 13,
      "l": 17,
      "be": 0,
      "wr": 0.4333,
      "pf": 0.636,
      "net_pts": -115.25,
      "avg_win": 15.462,
      "avg_loss": -18.603
    },
    {
      "year": "2016",
      "variant": "no_be",
      "smt": true,
      "side": "LONG",
      "n": 0,
      "w": 0,
      "l": 0,
      "be": 0,
      "wr": 0.0,
      "pf": 0.0,
      "net_pts": 0,
      "avg_win": 0.0,
      "avg_loss": 0.0
    },
    {
      "year": "2017",
      "variant": "no_be",
      "smt": true,
      "side": "LONG",
      "n": 1,
      "w": 1,
      "l": 0,
      "be": 0,
      "wr": 1.0,
      "pf": null,
      "net_pts": 5.0,
      "avg_win": 5.0,
      "avg_loss": 0.0
    },
    {
      "year": "2018",
      "variant": "no_be",
      "smt": true,
      "side": "LONG",
      "n": 1,
      "w": 1,
      "l": 0,
      "be": 0,
      "wr": 1.0,
      "pf": null,
      "net_pts": 5.25,
      "avg_win": 5.25,
      "avg_loss": 0.0
    },
    {
      "year": "2019",
      "variant": "no_be",
      "smt": true,
      "side": "LONG",
      "n": 0,
      "w": 0,
      "l": 0,
      "be": 0,
      "wr": 0.0,
      "pf": 0.0,
      "net_pts": 0,
      "avg_win": 0.0,
      "avg_loss": 0.0
    },
    {
      "year": "2020",
      "variant": "no_be",
      "smt": true,
      "side": "LONG",
      "n": 1,
      "w": 0,
      "l": 1,
      "be": 0,
      "wr": 0.0,
      "pf": 0.0,
      "net_pts": -14.25,
      "avg_win": 0.0,
      "avg_loss": -14.25
    },
    {
      "year": "2021",
      "variant": "no_be",
      "smt": true,
      "side": "LONG",
      "n": 2,
      "w": 2,
      "l": 0,
      "be": 0,
      "wr": 1.0,
      "pf": null,
      "net_pts": 27.75,
      "avg_win": 13.875,
      "avg_loss": 0.0
    },
    {
      "year": "2022",
      "variant": "no_be",
      "smt": true,
      "side": "LONG",
      "n": 1,
      "w": 0,
      "l": 1,
      "be": 0,
      "wr": 0.0,
      "pf": 0.0,
      "net_pts": -20.5,
      "avg_win": 0.0,
      "avg_loss": -20.5
    },
    {
      "year": "2023",
      "variant": "no_be",
      "smt": true,
      "side": "LONG",
      "n": 0,
      "w": 0,
      "l": 0,
      "be": 0,
      "wr": 0.0,
      "pf": 0.0,
      "net_pts": 0,
      "avg_win": 0.0,
      "avg_loss": 0.0
    },
    {
      "year": "2024",
      "variant": "no_be",
      "smt": true,
      "side": "LONG",
      "n": 3,
      "w": 1,
      "l": 2,
      "be": 0,
      "wr": 0.3333,
      "pf": 0.594,
      "net_pts": -32.25,
      "avg_win": 47.25,
      "avg_loss": -39.75
    },
    {
      "year": "ALL",
      "variant": "no_be",
      "smt": true,
      "side": "LONG",
      "n": 9,
      "w": 5,
      "l": 4,
      "be": 0,
      "wr": 0.5556,
      "pf": 0.746,
      "net_pts": -29.0,
      "avg_win": 17.05,
      "avg_loss": -28.562
    },
    {
      "year": "2016",
      "variant": "no_be",
      "smt": true,
      "side": "SHORT",
      "n": 1,
      "w": 0,
      "l": 1,
      "be": 0,
      "wr": 0.0,
      "pf": 0.0,
      "net_pts": -4.0,
      "avg_win": 0.0,
      "avg_loss": -4.0
    },
    {
      "year": "2017",
      "variant": "no_be",
      "smt": true,
      "side": "SHORT",
      "n": 3,
      "w": 1,
      "l": 2,
      "be": 0,
      "wr": 0.3333,
      "pf": 0.375,
      "net_pts": -5.0,
      "avg_win": 3.0,
      "avg_loss": -4.0
    },
    {
      "year": "2018",
      "variant": "no_be",
      "smt": true,
      "side": "SHORT",
      "n": 2,
      "w": 2,
      "l": 0,
      "be": 0,
      "wr": 1.0,
      "pf": null,
      "net_pts": 38.0,
      "avg_win": 19.0,
      "avg_loss": 0.0
    },
    {
      "year": "2019",
      "variant": "no_be",
      "smt": true,
      "side": "SHORT",
      "n": 4,
      "w": 2,
      "l": 2,
      "be": 0,
      "wr": 0.5,
      "pf": 0.985,
      "net_pts": -0.25,
      "avg_win": 8.25,
      "avg_loss": -8.375
    },
    {
      "year": "2020",
      "variant": "no_be",
      "smt": true,
      "side": "SHORT",
      "n": 3,
      "w": 0,
      "l": 3,
      "be": 0,
      "wr": 0.0,
      "pf": 0.0,
      "net_pts": -38.25,
      "avg_win": 0.0,
      "avg_loss": -12.75
    },
    {
      "year": "2021",
      "variant": "no_be",
      "smt": true,
      "side": "SHORT",
      "n": 3,
      "w": 1,
      "l": 2,
      "be": 0,
      "wr": 0.3333,
      "pf": 0.391,
      "net_pts": -26.5,
      "avg_win": 17.0,
      "avg_loss": -21.75
    },
    {
      "year": "2022",
      "variant": "no_be",
      "smt": true,
      "side": "SHORT",
      "n": 1,
      "w": 0,
      "l": 1,
      "be": 0,
      "wr": 0.0,
      "pf": 0.0,
      "net_pts": -22.5,
      "avg_win": 0.0,
      "avg_loss": -22.5
    },
    {
      "year": "2023",
      "variant": "no_be",
      "smt": true,
      "side": "SHORT",
      "n": 3,
      "w": 1,
      "l": 2,
      "be": 0,
      "wr": 0.3333,
      "pf": 0.377,
      "net_pts": -43.0,
      "avg_win": 26.0,
      "avg_loss": -34.5
    },
    {
      "year": "2024",
      "variant": "no_be",
      "smt": true,
      "side": "SHORT",
      "n": 1,
      "w": 1,
      "l": 0,
      "be": 0,
      "wr": 1.0,
      "pf": null,
      "net_pts": 15.25,
      "avg_win": 15.25,
      "avg_loss": 0.0
    },
    {
      "year": "ALL",
      "variant": "no_be",
      "smt": true,
      "side": "SHORT",
      "n": 21,
      "w": 8,
      "l": 13,
      "be": 0,
      "wr": 0.381,
      "pf": 0.573,
      "net_pts": -86.25,
      "avg_win": 14.469,
      "avg_loss": -15.538
    },
    {
      "year": "2016",
      "variant": "be_50",
      "smt": false,
      "side": "BOTH",
      "n": 4,
      "w": 1,
      "l": 3,
      "be": 0,
      "wr": 0.25,
      "pf": 1.178,
      "net_pts": 2.0,
      "avg_win": 13.25,
      "avg_loss": -3.75
    },
    {
      "year": "2017",
      "variant": "be_50",
      "smt": false,
      "side": "BOTH",
      "n": 4,
      "w": 0,
      "l": 2,
      "be": 2,
      "wr": 0.0,
      "pf": 0.0,
      "net_pts": -8.0,
      "avg_win": 0.0,
      "avg_loss": -4.0
    },
    {
      "year": "2018",
      "variant": "be_50",
      "smt": false,
      "side": "BOTH",
      "n": 3,
      "w": 3,
      "l": 0,
      "be": 0,
      "wr": 1.0,
      "pf": null,
      "net_pts": 43.25,
      "avg_win": 14.417,
      "avg_loss": 0.0
    },
    {
      "year": "2019",
      "variant": "be_50",
      "smt": false,
      "side": "BOTH",
      "n": 6,
      "w": 1,
      "l": 3,
      "be": 2,
      "wr": 0.25,
      "pf": 0.36,
      "net_pts": -14.25,
      "avg_win": 8.0,
      "avg_loss": -7.417
    },
    {
      "year": "2020",
      "variant": "be_50",
      "smt": false,
      "side": "BOTH",
      "n": 7,
      "w": 0,
      "l": 6,
      "be": 1,
      "wr": 0.0,
      "pf": 0.0,
      "net_pts": -130.0,
      "avg_win": 0.0,
      "avg_loss": -21.667
    },
    {
      "year": "2021",
      "variant": "be_50",
      "smt": false,
      "side": "BOTH",
      "n": 5,
      "w": 3,
      "l": 1,
      "be": 1,
      "wr": 0.75,
      "pf": 3.51,
      "net_pts": 32.0,
      "avg_win": 14.917,
      "avg_loss": -12.75
    },
    {
      "year": "2022",
      "variant": "be_50",
      "smt": false,
      "side": "BOTH",
      "n": 5,
      "w": 0,
      "l": 4,
      "be": 1,
      "wr": 0.0,
      "pf": 0.0,
      "net_pts": -156.5,
      "avg_win": 0.0,
      "avg_loss": -39.125
    },
    {
      "year": "2023",
      "variant": "be_50",
      "smt": false,
      "side": "BOTH",
      "n": 7,
      "w": 1,
      "l": 3,
      "be": 3,
      "wr": 0.25,
      "pf": 0.329,
      "net_pts": -53.0,
      "avg_win": 26.0,
      "avg_loss": -26.333
    },
    {
      "year": "2024",
      "variant": "be_50",
      "smt": false,
      "side": "BOTH",
      "n": 7,
      "w": 1,
      "l": 3,
      "be": 3,
      "wr": 0.25,
      "pf": 0.286,
      "net_pts": -81.0,
      "avg_win": 32.5,
      "avg_loss": -37.833
    },
    {
      "year": "ALL",
      "variant": "be_50",
      "smt": false,
      "side": "BOTH",
      "n": 48,
      "w": 10,
      "l": 25,
      "be": 13,
      "wr": 0.2857,
      "pf": 0.315,
      "net_pts": -365.5,
      "avg_win": 16.775,
      "avg_loss": -21.33
    },
    {
      "year": "2016",
      "variant": "be_50",
      "smt": false,
      "side": "LONG",
      "n": 1,
      "w": 1,
      "l": 0,
      "be": 0,
      "wr": 1.0,
      "pf": null,
      "net_pts": 13.25,
      "avg_win": 13.25,
      "avg_loss": 0.0
    },
    {
      "year": "2017",
      "variant": "be_50",
      "smt": false,
      "side": "LONG",
      "n": 1,
      "w": 0,
      "l": 0,
      "be": 1,
      "wr": 0.0,
      "pf": 0.0,
      "net_pts": 0,
      "avg_win": 0.0,
      "avg_loss": 0.0
    },
    {
      "year": "2018",
      "variant": "be_50",
      "smt": false,
      "side": "LONG",
      "n": 1,
      "w": 1,
      "l": 0,
      "be": 0,
      "wr": 1.0,
      "pf": null,
      "net_pts": 5.25,
      "avg_win": 5.25,
      "avg_loss": 0.0
    },
    {
      "year": "2019",
      "variant": "be_50",
      "smt": false,
      "side": "LONG",
      "n": 1,
      "w": 0,
      "l": 0,
      "be": 1,
      "wr": 0.0,
      "pf": 0.0,
      "net_pts": 0,
      "avg_win": 0.0,
      "avg_loss": 0.0
    },
    {
      "year": "2020",
      "variant": "be_50",
      "smt": false,
      "side": "LONG",
      "n": 3,
      "w": 0,
      "l": 2,
      "be": 1,
      "wr": 0.0,
      "pf": 0.0,
      "net_pts": -39.75,
      "avg_win": 0.0,
      "avg_loss": -19.875
    },
    {
      "year": "2021",
      "variant": "be_50",
      "smt": false,
      "side": "LONG",
      "n": 2,
      "w": 2,
      "l": 0,
      "be": 0,
      "wr": 1.0,
      "pf": null,
      "net_pts": 27.75,
      "avg_win": 13.875,
      "avg_loss": 0.0
    },
    {
      "year": "2022",
      "variant": "be_50",
      "smt": false,
      "side": "LONG",
      "n": 3,
      "w": 0,
      "l": 3,
      "be": 0,
      "wr": 0.0,
      "pf": 0.0,
      "net_pts": -117.75,
      "avg_win": 0.0,
      "avg_loss": -39.25
    },
    {
      "year": "2023",
      "variant": "be_50",
      "smt": false,
      "side": "LONG",
      "n": 4,
      "w": 0,
      "l": 2,
      "be": 2,
      "wr": 0.0,
      "pf": 0.0,
      "net_pts": -52.25,
      "avg_win": 0.0,
      "avg_loss": -26.125
    },
    {
      "year": "2024",
      "variant": "be_50",
      "smt": false,
      "side": "LONG",
      "n": 4,
      "w": 0,
      "l": 2,
      "be": 2,
      "wr": 0.0,
      "pf": 0.0,
      "net_pts": -52.25,
      "avg_win": 0.0,
      "avg_loss": -26.125
    },
    {
      "year": "ALL",
      "variant": "be_50",
      "smt": false,
      "side": "LONG",
      "n": 20,
      "w": 4,
      "l": 9,
      "be": 7,
      "wr": 0.3077,
      "pf": 0.177,
      "net_pts": -215.75,
      "avg_win": 11.562,
      "avg_loss": -29.111
    },
    {
      "year": "2016",
      "variant": "be_50",
      "smt": false,
      "side": "SHORT",
      "n": 3,
      "w": 0,
      "l": 3,
      "be": 0,
      "wr": 0.0,
      "pf": 0.0,
      "net_pts": -11.25,
      "avg_win": 0.0,
      "avg_loss": -3.75
    },
    {
      "year": "2017",
      "variant": "be_50",
      "smt": false,
      "side": "SHORT",
      "n": 3,
      "w": 0,
      "l": 2,
      "be": 1,
      "wr": 0.0,
      "pf": 0.0,
      "net_pts": -8.0,
      "avg_win": 0.0,
      "avg_loss": -4.0
    },
    {
      "year": "2018",
      "variant": "be_50",
      "smt": false,
      "side": "SHORT",
      "n": 2,
      "w": 2,
      "l": 0,
      "be": 0,
      "wr": 1.0,
      "pf": null,
      "net_pts": 38.0,
      "avg_win": 19.0,
      "avg_loss": 0.0
    },
    {
      "year": "2019",
      "variant": "be_50",
      "smt": false,
      "side": "SHORT",
      "n": 5,
      "w": 1,
      "l": 3,
      "be": 1,
      "wr": 0.25,
      "pf": 0.36,
      "net_pts": -14.25,
      "avg_win": 8.0,
      "avg_loss": -7.417
    },
    {
      "year": "2020",
      "variant": "be_50",
      "smt": false,
      "side": "SHORT",
      "n": 4,
      "w": 0,
      "l": 4,
      "be": 0,
      "wr": 0.0,
      "pf": 0.0,
      "net_pts": -90.25,
      "avg_win": 0.0,
      "avg_loss": -22.562
    },
    {
      "year": "2021",
      "variant": "be_50",
      "smt": false,
      "side": "SHORT",
      "n": 3,
      "w": 1,
      "l": 1,
      "be": 1,
      "wr": 0.5,
      "pf": 1.333,
      "net_pts": 4.25,
      "avg_win": 17.0,
      "avg_loss": -12.75
    },
    {
      "year": "2022",
      "variant": "be_50",
      "smt": false,
      "side": "SHORT",
      "n": 2,
      "w": 0,
      "l": 1,
      "be": 1,
      "wr": 0.0,
      "pf": 0.0,
      "net_pts": -38.75,
      "avg_win": 0.0,
      "avg_loss": -38.75
    },
    {
      "year": "2023",
      "variant": "be_50",
      "smt": false,
      "side": "SHORT",
      "n": 3,
      "w": 1,
      "l": 1,
      "be": 1,
      "wr": 0.5,
      "pf": 0.972,
      "net_pts": -0.75,
      "avg_win": 26.0,
      "avg_loss": -26.75
    },
    {
      "year": "2024",
      "variant": "be_50",
      "smt": false,
      "side": "SHORT",
      "n": 3,
      "w": 1,
      "l": 1,
      "be": 1,
      "wr": 0.5,
      "pf": 0.531,
      "net_pts": -28.75,
      "avg_win": 32.5,
      "avg_loss": -61.25
    },
    {
      "year": "ALL",
      "variant": "be_50",
      "smt": false,
      "side": "SHORT",
      "n": 28,
      "w": 6,
      "l": 16,
      "be": 6,
      "wr": 0.2727,
      "pf": 0.448,
      "net_pts": -149.75,
      "avg_win": 20.25,
      "avg_loss": -16.953
    },
    {
      "year": "2016",
      "variant": "be_50",
      "smt": true,
      "side": "BOTH",
      "n": 1,
      "w": 0,
      "l": 1,
      "be": 0,
      "wr": 0.0,
      "pf": 0.0,
      "net_pts": -4.0,
      "avg_win": 0.0,
      "avg_loss": -4.0
    },
    {
      "year": "2017",
      "variant": "be_50",
      "smt": true,
      "side": "BOTH",
      "n": 4,
      "w": 0,
      "l": 2,
      "be": 2,
      "wr": 0.0,
      "pf": 0.0,
      "net_pts": -8.0,
      "avg_win": 0.0,
      "avg_loss": -4.0
    },
    {
      "year": "2018",
      "variant": "be_50",
      "smt": true,
      "side": "BOTH",
      "n": 3,
      "w": 3,
      "l": 0,
      "be": 0,
      "wr": 1.0,
      "pf": null,
      "net_pts": 43.25,
      "avg_win": 14.417,
      "avg_loss": 0.0
    },
    {
      "year": "2019",
      "variant": "be_50",
      "smt": true,
      "side": "BOTH",
      "n": 4,
      "w": 1,
      "l": 2,
      "be": 1,
      "wr": 0.3333,
      "pf": 0.478,
      "net_pts": -8.75,
      "avg_win": 8.0,
      "avg_loss": -8.375
    },
    {
      "year": "2020",
      "variant": "be_50",
      "smt": true,
      "side": "BOTH",
      "n": 4,
      "w": 0,
      "l": 4,
      "be": 0,
      "wr": 0.0,
      "pf": 0.0,
      "net_pts": -52.5,
      "avg_win": 0.0,
      "avg_loss": -13.125
    },
    {
      "year": "2021",
      "variant": "be_50",
      "smt": true,
      "side": "BOTH",
      "n": 5,
      "w": 3,
      "l": 1,
      "be": 1,
      "wr": 0.75,
      "pf": 3.51,
      "net_pts": 32.0,
      "avg_win": 14.917,
      "avg_loss": -12.75
    },
    {
      "year": "2022",
      "variant": "be_50",
      "smt": true,
      "side": "BOTH",
      "n": 2,
      "w": 0,
      "l": 1,
      "be": 1,
      "wr": 0.0,
      "pf": 0.0,
      "net_pts": -20.5,
      "avg_win": 0.0,
      "avg_loss": -20.5
    },
    {
      "year": "2023",
      "variant": "be_50",
      "smt": true,
      "side": "BOTH",
      "n": 3,
      "w": 1,
      "l": 1,
      "be": 1,
      "wr": 0.5,
      "pf": 0.972,
      "net_pts": -0.75,
      "avg_win": 26.0,
      "avg_loss": -26.75
    },
    {
      "year": "2024",
      "variant": "be_50",
      "smt": true,
      "side": "BOTH",
      "n": 4,
      "w": 0,
      "l": 1,
      "be": 3,
      "wr": 0.0,
      "pf": 0.0,
      "net_pts": -44.0,
      "avg_win": 0.0,
      "avg_loss": -44.0
    },
    {
      "year": "ALL",
      "variant": "be_50",
      "smt": true,
      "side": "BOTH",
      "n": 30,
      "w": 8,
      "l": 13,
      "be": 9,
      "wr": 0.381,
      "pf": 0.659,
      "net_pts": -63.25,
      "avg_win": 15.25,
      "avg_loss": -14.25
    },
    {
      "year": "2016",
      "variant": "be_50",
      "smt": true,
      "side": "LONG",
      "n": 0,
      "w": 0,
      "l": 0,
      "be": 0,
      "wr": 0.0,
      "pf": 0.0,
      "net_pts": 0,
      "avg_win": 0.0,
      "avg_loss": 0.0
    },
    {
      "year": "2017",
      "variant": "be_50",
      "smt": true,
      "side": "LONG",
      "n": 1,
      "w": 0,
      "l": 0,
      "be": 1,
      "wr": 0.0,
      "pf": 0.0,
      "net_pts": 0,
      "avg_win": 0.0,
      "avg_loss": 0.0
    },
    {
      "year": "2018",
      "variant": "be_50",
      "smt": true,
      "side": "LONG",
      "n": 1,
      "w": 1,
      "l": 0,
      "be": 0,
      "wr": 1.0,
      "pf": null,
      "net_pts": 5.25,
      "avg_win": 5.25,
      "avg_loss": 0.0
    },
    {
      "year": "2019",
      "variant": "be_50",
      "smt": true,
      "side": "LONG",
      "n": 0,
      "w": 0,
      "l": 0,
      "be": 0,
      "wr": 0.0,
      "pf": 0.0,
      "net_pts": 0,
      "avg_win": 0.0,
      "avg_loss": 0.0
    },
    {
      "year": "2020",
      "variant": "be_50",
      "smt": true,
      "side": "LONG",
      "n": 1,
      "w": 0,
      "l": 1,
      "be": 0,
      "wr": 0.0,
      "pf": 0.0,
      "net_pts": -14.25,
      "avg_win": 0.0,
      "avg_loss": -14.25
    },
    {
      "year": "2021",
      "variant": "be_50",
      "smt": true,
      "side": "LONG",
      "n": 2,
      "w": 2,
      "l": 0,
      "be": 0,
      "wr": 1.0,
      "pf": null,
      "net_pts": 27.75,
      "avg_win": 13.875,
      "avg_loss": 0.0
    },
    {
      "year": "2022",
      "variant": "be_50",
      "smt": true,
      "side": "LONG",
      "n": 1,
      "w": 0,
      "l": 1,
      "be": 0,
      "wr": 0.0,
      "pf": 0.0,
      "net_pts": -20.5,
      "avg_win": 0.0,
      "avg_loss": -20.5
    },
    {
      "year": "2023",
      "variant": "be_50",
      "smt": true,
      "side": "LONG",
      "n": 0,
      "w": 0,
      "l": 0,
      "be": 0,
      "wr": 0.0,
      "pf": 0.0,
      "net_pts": 0,
      "avg_win": 0.0,
      "avg_loss": 0.0
    },
    {
      "year": "2024",
      "variant": "be_50",
      "smt": true,
      "side": "LONG",
      "n": 3,
      "w": 0,
      "l": 1,
      "be": 2,
      "wr": 0.0,
      "pf": 0.0,
      "net_pts": -44.0,
      "avg_win": 0.0,
      "avg_loss": -44.0
    },
    {
      "year": "ALL",
      "variant": "be_50",
      "smt": true,
      "side": "LONG",
      "n": 9,
      "w": 3,
      "l": 3,
      "be": 3,
      "wr": 0.5,
      "pf": 0.419,
      "net_pts": -45.75,
      "avg_win": 11.0,
      "avg_loss": -26.25
    },
    {
      "year": "2016",
      "variant": "be_50",
      "smt": true,
      "side": "SHORT",
      "n": 1,
      "w": 0,
      "l": 1,
      "be": 0,
      "wr": 0.0,
      "pf": 0.0,
      "net_pts": -4.0,
      "avg_win": 0.0,
      "avg_loss": -4.0
    },
    {
      "year": "2017",
      "variant": "be_50",
      "smt": true,
      "side": "SHORT",
      "n": 3,
      "w": 0,
      "l": 2,
      "be": 1,
      "wr": 0.0,
      "pf": 0.0,
      "net_pts": -8.0,
      "avg_win": 0.0,
      "avg_loss": -4.0
    },
    {
      "year": "2018",
      "variant": "be_50",
      "smt": true,
      "side": "SHORT",
      "n": 2,
      "w": 2,
      "l": 0,
      "be": 0,
      "wr": 1.0,
      "pf": null,
      "net_pts": 38.0,
      "avg_win": 19.0,
      "avg_loss": 0.0
    },
    {
      "year": "2019",
      "variant": "be_50",
      "smt": true,
      "side": "SHORT",
      "n": 4,
      "w": 1,
      "l": 2,
      "be": 1,
      "wr": 0.3333,
      "pf": 0.478,
      "net_pts": -8.75,
      "avg_win": 8.0,
      "avg_loss": -8.375
    },
    {
      "year": "2020",
      "variant": "be_50",
      "smt": true,
      "side": "SHORT",
      "n": 3,
      "w": 0,
      "l": 3,
      "be": 0,
      "wr": 0.0,
      "pf": 0.0,
      "net_pts": -38.25,
      "avg_win": 0.0,
      "avg_loss": -12.75
    },
    {
      "year": "2021",
      "variant": "be_50",
      "smt": true,
      "side": "SHORT",
      "n": 3,
      "w": 1,
      "l": 1,
      "be": 1,
      "wr": 0.5,
      "pf": 1.333,
      "net_pts": 4.25,
      "avg_win": 17.0,
      "avg_loss": -12.75
    },
    {
      "year": "2022",
      "variant": "be_50",
      "smt": true,
      "side": "SHORT",
      "n": 1,
      "w": 0,
      "l": 0,
      "be": 1,
      "wr": 0.0,
      "pf": 0.0,
      "net_pts": 0,
      "avg_win": 0.0,
      "avg_loss": 0.0
    },
    {
      "year": "2023",
      "variant": "be_50",
      "smt": true,
      "side": "SHORT",
      "n": 3,
      "w": 1,
      "l": 1,
      "be": 1,
      "wr": 0.5,
      "pf": 0.972,
      "net_pts": -0.75,
      "avg_win": 26.0,
      "avg_loss": -26.75
    },
    {
      "year": "2024",
      "variant": "be_50",
      "smt": true,
      "side": "SHORT",
      "n": 1,
      "w": 0,
      "l": 0,
      "be": 1,
      "wr": 0.0,
      "pf": 0.0,
      "net_pts": 0,
      "avg_win": 0.0,
      "avg_loss": 0.0
    },
    {
      "year": "ALL",
      "variant": "be_50",
      "smt": true,
      "side": "SHORT",
      "n": 21,
      "w": 5,
      "l": 10,
      "be": 6,
      "wr": 0.3333,
      "pf": 0.836,
      "net_pts": -17.5,
      "avg_win": 17.8,
      "avg_loss": -10.65
    },
    {
      "year": "2016",
      "variant": "tp1_be",
      "smt": false,
      "side": "BOTH",
      "n": 4,
      "w": 1,
      "l": 3,
      "be": 0,
      "wr": 0.25,
      "pf": 1.006,
      "net_pts": 0.06,
      "avg_win": 11.312,
      "avg_loss": -3.75
    },
    {
      "year": "2017",
      "variant": "tp1_be",
      "smt": false,
      "side": "BOTH",
      "n": 4,
      "w": 2,
      "l": 2,
      "be": 0,
      "wr": 0.5,
      "pf": 0.25,
      "net_pts": -6.0,
      "avg_win": 1.0,
      "avg_loss": -4.0
    },
    {
      "year": "2018",
      "variant": "tp1_be",
      "smt": false,
      "side": "BOTH",
      "n": 3,
      "w": 3,
      "l": 0,
      "be": 0,
      "wr": 1.0,
      "pf": null,
      "net_pts": 32.44,
      "avg_win": 10.812,
      "avg_loss": 0.0
    },
    {
      "year": "2019",
      "variant": "tp1_be",
      "smt": false,
      "side": "BOTH",
      "n": 6,
      "w": 3,
      "l": 3,
      "be": 0,
      "wr": 0.5,
      "pf": 0.649,
      "net_pts": -7.81,
      "avg_win": 4.812,
      "avg_loss": -7.417
    },
    {
      "year": "2020",
      "variant": "tp1_be",
      "smt": false,
      "side": "BOTH",
      "n": 7,
      "w": 1,
      "l": 6,
      "be": 0,
      "wr": 0.1429,
      "pf": 0.063,
      "net_pts": -121.75,
      "avg_win": 8.25,
      "avg_loss": -21.667
    },
    {
      "year": "2021",
      "variant": "tp1_be",
      "smt": false,
      "side": "BOTH",
      "n": 5,
      "w": 4,
      "l": 1,
      "be": 0,
      "wr": 0.8,
      "pf": 3.711,
      "net_pts": 34.56,
      "avg_win": 11.828,
      "avg_loss": -12.75
    },
    {
      "year": "2022",
      "variant": "tp1_be",
      "smt": false,
      "side": "BOTH",
      "n": 5,
      "w": 1,
      "l": 4,
      "be": 0,
      "wr": 0.2,
      "pf": 0.046,
      "net_pts": -149.38,
      "avg_win": 7.125,
      "avg_loss": -39.125
    },
    {
      "year": "2023",
      "variant": "tp1_be",
      "smt": false,
      "side": "BOTH",
      "n": 7,
      "w": 4,
      "l": 3,
      "be": 0,
      "wr": 0.5714,
      "pf": 0.531,
      "net_pts": -37.06,
      "avg_win": 10.484,
      "avg_loss": -26.333
    },
    {
      "year": "2024",
      "variant": "tp1_be",
      "smt": false,
      "side": "BOTH",
      "n": 7,
      "w": 4,
      "l": 3,
      "be": 0,
      "wr": 0.5714,
      "pf": 0.469,
      "net_pts": -60.25,
      "avg_win": 13.312,
      "avg_loss": -37.833
    },
    {
      "year": "ALL",
      "variant": "tp1_be",
      "smt": false,
      "side": "BOTH",
      "n": 48,
      "w": 23,
      "l": 25,
      "be": 0,
      "wr": 0.4792,
      "pf": 0.409,
      "net_pts": -315.19,
      "avg_win": 9.481,
      "avg_loss": -21.33
    },
    {
      "year": "2016",
      "variant": "tp1_be",
      "smt": false,
      "side": "LONG",
      "n": 1,
      "w": 1,
      "l": 0,
      "be": 0,
      "wr": 1.0,
      "pf": null,
      "net_pts": 11.31,
      "avg_win": 11.312,
      "avg_loss": 0.0
    },
    {
      "year": "2017",
      "variant": "tp1_be",
      "smt": false,
      "side": "LONG",
      "n": 1,
      "w": 1,
      "l": 0,
      "be": 0,
      "wr": 1.0,
      "pf": null,
      "net_pts": 1.25,
      "avg_win": 1.25,
      "avg_loss": 0.0
    },
    {
      "year": "2018",
      "variant": "tp1_be",
      "smt": false,
      "side": "LONG",
      "n": 1,
      "w": 1,
      "l": 0,
      "be": 0,
      "wr": 1.0,
      "pf": null,
      "net_pts": 3.94,
      "avg_win": 3.938,
      "avg_loss": 0.0
    },
    {
      "year": "2019",
      "variant": "tp1_be",
      "smt": false,
      "side": "LONG",
      "n": 1,
      "w": 1,
      "l": 0,
      "be": 0,
      "wr": 1.0,
      "pf": null,
      "net_pts": 4.31,
      "avg_win": 4.312,
      "avg_loss": 0.0
    },
    {
      "year": "2020",
      "variant": "tp1_be",
      "smt": false,
      "side": "LONG",
      "n": 3,
      "w": 1,
      "l": 2,
      "be": 0,
      "wr": 0.3333,
      "pf": 0.208,
      "net_pts": -31.5,
      "avg_win": 8.25,
      "avg_loss": -19.875
    },
    {
      "year": "2021",
      "variant": "tp1_be",
      "smt": false,
      "side": "LONG",
      "n": 2,
      "w": 2,
      "l": 0,
      "be": 0,
      "wr": 1.0,
      "pf": null,
      "net_pts": 27.75,
      "avg_win": 13.875,
      "avg_loss": 0.0
    },
    {
      "year": "2022",
      "variant": "tp1_be",
      "smt": false,
      "side": "LONG",
      "n": 3,
      "w": 0,
      "l": 3,
      "be": 0,
      "wr": 0.0,
      "pf": 0.0,
      "net_pts": -117.75,
      "avg_win": 0.0,
      "avg_loss": -39.25
    },
    {
      "year": "2023",
      "variant": "tp1_be",
      "smt": false,
      "side": "LONG",
      "n": 4,
      "w": 2,
      "l": 2,
      "be": 0,
      "wr": 0.5,
      "pf": 0.208,
      "net_pts": -41.38,
      "avg_win": 5.438,
      "avg_loss": -26.125
    },
    {
      "year": "2024",
      "variant": "tp1_be",
      "smt": false,
      "side": "LONG",
      "n": 4,
      "w": 2,
      "l": 2,
      "be": 0,
      "wr": 0.5,
      "pf": 0.324,
      "net_pts": -35.31,
      "avg_win": 8.469,
      "avg_loss": -26.125
    },
    {
      "year": "ALL",
      "variant": "tp1_be",
      "smt": false,
      "side": "LONG",
      "n": 20,
      "w": 11,
      "l": 9,
      "be": 0,
      "wr": 0.55,
      "pf": 0.323,
      "net_pts": -177.38,
      "avg_win": 7.693,
      "avg_loss": -29.111
    },
    {
      "year": "2016",
      "variant": "tp1_be",
      "smt": false,
      "side": "SHORT",
      "n": 3,
      "w": 0,
      "l": 3,
      "be": 0,
      "wr": 0.0,
      "pf": 0.0,
      "net_pts": -11.25,
      "avg_win": 0.0,
      "avg_loss": -3.75
    },
    {
      "year": "2017",
      "variant": "tp1_be",
      "smt": false,
      "side": "SHORT",
      "n": 3,
      "w": 1,
      "l": 2,
      "be": 0,
      "wr": 0.3333,
      "pf": 0.094,
      "net_pts": -7.25,
      "avg_win": 0.75,
      "avg_loss": -4.0
    },
    {
      "year": "2018",
      "variant": "tp1_be",
      "smt": false,
      "side": "SHORT",
      "n": 2,
      "w": 2,
      "l": 0,
      "be": 0,
      "wr": 1.0,
      "pf": null,
      "net_pts": 28.5,
      "avg_win": 14.25,
      "avg_loss": 0.0
    },
    {
      "year": "2019",
      "variant": "tp1_be",
      "smt": false,
      "side": "SHORT",
      "n": 5,
      "w": 2,
      "l": 3,
      "be": 0,
      "wr": 0.4,
      "pf": 0.455,
      "net_pts": -12.12,
      "avg_win": 5.062,
      "avg_loss": -7.417
    },
    {
      "year": "2020",
      "variant": "tp1_be",
      "smt": false,
      "side": "SHORT",
      "n": 4,
      "w": 0,
      "l": 4,
      "be": 0,
      "wr": 0.0,
      "pf": 0.0,
      "net_pts": -90.25,
      "avg_win": 0.0,
      "avg_loss": -22.562
    },
    {
      "year": "2021",
      "variant": "tp1_be",
      "smt": false,
      "side": "SHORT",
      "n": 3,
      "w": 2,
      "l": 1,
      "be": 0,
      "wr": 0.6667,
      "pf": 1.534,
      "net_pts": 6.81,
      "avg_win": 9.781,
      "avg_loss": -12.75
    },
    {
      "year": "2022",
      "variant": "tp1_be",
      "smt": false,
      "side": "SHORT",
      "n": 2,
      "w": 1,
      "l": 1,
      "be": 0,
      "wr": 0.5,
      "pf": 0.184,
      "net_pts": -31.62,
      "avg_win": 7.125,
      "avg_loss": -38.75
    },
    {
      "year": "2023",
      "variant": "tp1_be",
      "smt": false,
      "side": "SHORT",
      "n": 3,
      "w": 2,
      "l": 1,
      "be": 0,
      "wr": 0.6667,
      "pf": 1.161,
      "net_pts": 4.31,
      "avg_win": 15.531,
      "avg_loss": -26.75
    },
    {
      "year": "2024",
      "variant": "tp1_be",
      "smt": false,
      "side": "SHORT",
      "n": 3,
      "w": 2,
      "l": 1,
      "be": 0,
      "wr": 0.6667,
      "pf": 0.593,
      "net_pts": -24.94,
      "avg_win": 18.156,
      "avg_loss": -61.25
    },
    {
      "year": "ALL",
      "variant": "tp1_be",
      "smt": false,
      "side": "SHORT",
      "n": 28,
      "w": 12,
      "l": 16,
      "be": 0,
      "wr": 0.4286,
      "pf": 0.492,
      "net_pts": -137.81,
      "avg_win": 11.12,
      "avg_loss": -16.953
    },
    {
      "year": "2016",
      "variant": "tp1_be",
      "smt": true,
      "side": "BOTH",
      "n": 1,
      "w": 0,
      "l": 1,
      "be": 0,
      "wr": 0.0,
      "pf": 0.0,
      "net_pts": -4.0,
      "avg_win": 0.0,
      "avg_loss": -4.0
    },
    {
      "year": "2017",
      "variant": "tp1_be",
      "smt": true,
      "side": "BOTH",
      "n": 4,
      "w": 2,
      "l": 2,
      "be": 0,
      "wr": 0.5,
      "pf": 0.25,
      "net_pts": -6.0,
      "avg_win": 1.0,
      "avg_loss": -4.0
    },
    {
      "year": "2018",
      "variant": "tp1_be",
      "smt": true,
      "side": "BOTH",
      "n": 3,
      "w": 3,
      "l": 0,
      "be": 0,
      "wr": 1.0,
      "pf": null,
      "net_pts": 32.44,
      "avg_win": 10.812,
      "avg_loss": 0.0
    },
    {
      "year": "2019",
      "variant": "tp1_be",
      "smt": true,
      "side": "BOTH",
      "n": 4,
      "w": 2,
      "l": 2,
      "be": 0,
      "wr": 0.5,
      "pf": 0.604,
      "net_pts": -6.62,
      "avg_win": 5.062,
      "avg_loss": -8.375
    },
    {
      "year": "2020",
      "variant": "tp1_be",
      "smt": true,
      "side": "BOTH",
      "n": 4,
      "w": 0,
      "l": 4,
      "be": 0,
      "wr": 0.0,
      "pf": 0.0,
      "net_pts": -52.5,
      "avg_win": 0.0,
      "avg_loss": -13.125
    },
    {
      "year": "2021",
      "variant": "tp1_be",
      "smt": true,
      "side": "BOTH",
      "n": 5,
      "w": 4,
      "l": 1,
      "be": 0,
      "wr": 0.8,
      "pf": 3.711,
      "net_pts": 34.56,
      "avg_win": 11.828,
      "avg_loss": -12.75
    },
    {
      "year": "2022",
      "variant": "tp1_be",
      "smt": true,
      "side": "BOTH",
      "n": 2,
      "w": 1,
      "l": 1,
      "be": 0,
      "wr": 0.5,
      "pf": 0.348,
      "net_pts": -13.38,
      "avg_win": 7.125,
      "avg_loss": -20.5
    },
    {
      "year": "2023",
      "variant": "tp1_be",
      "smt": true,
      "side": "BOTH",
      "n": 3,
      "w": 2,
      "l": 1,
      "be": 0,
      "wr": 0.6667,
      "pf": 1.161,
      "net_pts": 4.31,
      "avg_win": 15.531,
      "avg_loss": -26.75
    },
    {
      "year": "2024",
      "variant": "tp1_be",
      "smt": true,
      "side": "BOTH",
      "n": 4,
      "w": 3,
      "l": 1,
      "be": 0,
      "wr": 0.75,
      "pf": 0.472,
      "net_pts": -23.25,
      "avg_win": 6.917,
      "avg_loss": -44.0
    },
    {
      "year": "ALL",
      "variant": "tp1_be",
      "smt": true,
      "side": "BOTH",
      "n": 30,
      "w": 17,
      "l": 13,
      "be": 0,
      "wr": 0.5667,
      "pf": 0.814,
      "net_pts": -34.44,
      "avg_win": 8.871,
      "avg_loss": -14.25
    },
    {
      "year": "2016",
      "variant": "tp1_be",
      "smt": true,
      "side": "LONG",
      "n": 0,
      "w": 0,
      "l": 0,
      "be": 0,
      "wr": 0.0,
      "pf": 0.0,
      "net_pts": 0,
      "avg_win": 0.0,
      "avg_loss": 0.0
    },
    {
      "year": "2017",
      "variant": "tp1_be",
      "smt": true,
      "side": "LONG",
      "n": 1,
      "w": 1,
      "l": 0,
      "be": 0,
      "wr": 1.0,
      "pf": null,
      "net_pts": 1.25,
      "avg_win": 1.25,
      "avg_loss": 0.0
    },
    {
      "year": "2018",
      "variant": "tp1_be",
      "smt": true,
      "side": "LONG",
      "n": 1,
      "w": 1,
      "l": 0,
      "be": 0,
      "wr": 1.0,
      "pf": null,
      "net_pts": 3.94,
      "avg_win": 3.938,
      "avg_loss": 0.0
    },
    {
      "year": "2019",
      "variant": "tp1_be",
      "smt": true,
      "side": "LONG",
      "n": 0,
      "w": 0,
      "l": 0,
      "be": 0,
      "wr": 0.0,
      "pf": 0.0,
      "net_pts": 0,
      "avg_win": 0.0,
      "avg_loss": 0.0
    },
    {
      "year": "2020",
      "variant": "tp1_be",
      "smt": true,
      "side": "LONG",
      "n": 1,
      "w": 0,
      "l": 1,
      "be": 0,
      "wr": 0.0,
      "pf": 0.0,
      "net_pts": -14.25,
      "avg_win": 0.0,
      "avg_loss": -14.25
    },
    {
      "year": "2021",
      "variant": "tp1_be",
      "smt": true,
      "side": "LONG",
      "n": 2,
      "w": 2,
      "l": 0,
      "be": 0,
      "wr": 1.0,
      "pf": null,
      "net_pts": 27.75,
      "avg_win": 13.875,
      "avg_loss": 0.0
    },
    {
      "year": "2022",
      "variant": "tp1_be",
      "smt": true,
      "side": "LONG",
      "n": 1,
      "w": 0,
      "l": 1,
      "be": 0,
      "wr": 0.0,
      "pf": 0.0,
      "net_pts": -20.5,
      "avg_win": 0.0,
      "avg_loss": -20.5
    },
    {
      "year": "2023",
      "variant": "tp1_be",
      "smt": true,
      "side": "LONG",
      "n": 0,
      "w": 0,
      "l": 0,
      "be": 0,
      "wr": 0.0,
      "pf": 0.0,
      "net_pts": 0,
      "avg_win": 0.0,
      "avg_loss": 0.0
    },
    {
      "year": "2024",
      "variant": "tp1_be",
      "smt": true,
      "side": "LONG",
      "n": 3,
      "w": 2,
      "l": 1,
      "be": 0,
      "wr": 0.6667,
      "pf": 0.385,
      "net_pts": -27.06,
      "avg_win": 8.469,
      "avg_loss": -44.0
    },
    {
      "year": "ALL",
      "variant": "tp1_be",
      "smt": true,
      "side": "LONG",
      "n": 9,
      "w": 6,
      "l": 3,
      "be": 0,
      "wr": 0.6667,
      "pf": 0.633,
      "net_pts": -28.88,
      "avg_win": 8.312,
      "avg_loss": -26.25
    },
    {
      "year": "2016",
      "variant": "tp1_be",
      "smt": true,
      "side": "SHORT",
      "n": 1,
      "w": 0,
      "l": 1,
      "be": 0,
      "wr": 0.0,
      "pf": 0.0,
      "net_pts": -4.0,
      "avg_win": 0.0,
      "avg_loss": -4.0
    },
    {
      "year": "2017",
      "variant": "tp1_be",
      "smt": true,
      "side": "SHORT",
      "n": 3,
      "w": 1,
      "l": 2,
      "be": 0,
      "wr": 0.3333,
      "pf": 0.094,
      "net_pts": -7.25,
      "avg_win": 0.75,
      "avg_loss": -4.0
    },
    {
      "year": "2018",
      "variant": "tp1_be",
      "smt": true,
      "side": "SHORT",
      "n": 2,
      "w": 2,
      "l": 0,
      "be": 0,
      "wr": 1.0,
      "pf": null,
      "net_pts": 28.5,
      "avg_win": 14.25,
      "avg_loss": 0.0
    },
    {
      "year": "2019",
      "variant": "tp1_be",
      "smt": true,
      "side": "SHORT",
      "n": 4,
      "w": 2,
      "l": 2,
      "be": 0,
      "wr": 0.5,
      "pf": 0.604,
      "net_pts": -6.62,
      "avg_win": 5.062,
      "avg_loss": -8.375
    },
    {
      "year": "2020",
      "variant": "tp1_be",
      "smt": true,
      "side": "SHORT",
      "n": 3,
      "w": 0,
      "l": 3,
      "be": 0,
      "wr": 0.0,
      "pf": 0.0,
      "net_pts": -38.25,
      "avg_win": 0.0,
      "avg_loss": -12.75
    },
    {
      "year": "2021",
      "variant": "tp1_be",
      "smt": true,
      "side": "SHORT",
      "n": 3,
      "w": 2,
      "l": 1,
      "be": 0,
      "wr": 0.6667,
      "pf": 1.534,
      "net_pts": 6.81,
      "avg_win": 9.781,
      "avg_loss": -12.75
    },
    {
      "year": "2022",
      "variant": "tp1_be",
      "smt": true,
      "side": "SHORT",
      "n": 1,
      "w": 1,
      "l": 0,
      "be": 0,
      "wr": 1.0,
      "pf": null,
      "net_pts": 7.12,
      "avg_win": 7.125,
      "avg_loss": 0.0
    },
    {
      "year": "2023",
      "variant": "tp1_be",
      "smt": true,
      "side": "SHORT",
      "n": 3,
      "w": 2,
      "l": 1,
      "be": 0,
      "wr": 0.6667,
      "pf": 1.161,
      "net_pts": 4.31,
      "avg_win": 15.531,
      "avg_loss": -26.75
    },
    {
      "year": "2024",
      "variant": "tp1_be",
      "smt": true,
      "side": "SHORT",
      "n": 1,
      "w": 1,
      "l": 0,
      "be": 0,
      "wr": 1.0,
      "pf": null,
      "net_pts": 3.81,
      "avg_win": 3.812,
      "avg_loss": 0.0
    },
    {
      "year": "ALL",
      "variant": "tp1_be",
      "smt": true,
      "side": "SHORT",
      "n": 21,
      "w": 11,
      "l": 10,
      "be": 0,
      "wr": 0.5238,
      "pf": 0.948,
      "net_pts": -5.56,
      "avg_win": 9.176,
      "avg_loss": -10.65
    }
  ],
  "trades": [
    {
      "ts": "2016-06-08T14:00:00Z",
      "year": 2016,
      "variant": "no_be",
      "smt": false,
      "side": "long",
      "pnl_pts": 13.25,
      "outcome": "timeout"
    },
    {
      "ts": "2016-06-08T14:00:00Z",
      "year": 2016,
      "variant": "be_50",
      "smt": false,
      "side": "long",
      "pnl_pts": 13.25,
      "outcome": "timeout"
    },
    {
      "ts": "2016-06-08T14:00:00Z",
      "year": 2016,
      "variant": "tp1_be",
      "smt": false,
      "side": "long",
      "pnl_pts": 11.3125,
      "outcome": "timeout"
    },
    {
      "ts": "2016-08-10T14:00:00Z",
      "year": 2016,
      "variant": "no_be",
      "smt": true,
      "side": "short",
      "pnl_pts": -4.0,
      "outcome": "loss"
    },
    {
      "ts": "2016-08-10T14:00:00Z",
      "year": 2016,
      "variant": "be_50",
      "smt": true,
      "side": "short",
      "pnl_pts": -4.0,
      "outcome": "loss"
    },
    {
      "ts": "2016-08-10T14:00:00Z",
      "year": 2016,
      "variant": "tp1_be",
      "smt": true,
      "side": "short",
      "pnl_pts": -4.0,
      "outcome": "loss"
    },
    {
      "ts": "2016-11-08T15:00:00Z",
      "year": 2016,
      "variant": "no_be",
      "smt": false,
      "side": "short",
      "pnl_pts": -3.25,
      "outcome": "loss"
    },
    {
      "ts": "2016-11-08T15:00:00Z",
      "year": 2016,
      "variant": "be_50",
      "smt": false,
      "side": "short",
      "pnl_pts": -3.25,
      "outcome": "loss"
    },
    {
      "ts": "2016-11-08T15:00:00Z",
      "year": 2016,
      "variant": "tp1_be",
      "smt": false,
      "side": "short",
      "pnl_pts": -3.25,
      "outcome": "loss"
    },
    {
      "ts": "2016-12-07T15:00:00Z",
      "year": 2016,
      "variant": "no_be",
      "smt": false,
      "side": "short",
      "pnl_pts": -4.0,
      "outcome": "loss"
    },
    {
      "ts": "2016-12-07T15:00:00Z",
      "year": 2016,
      "variant": "be_50",
      "smt": false,
      "side": "short",
      "pnl_pts": -4.0,
      "outcome": "loss"
    },
    {
      "ts": "2016-12-07T15:00:00Z",
      "year": 2016,
      "variant": "tp1_be",
      "smt": false,
      "side": "short",
      "pnl_pts": -4.0,
      "outcome": "loss"
    },
    {
      "ts": "2017-01-10T15:00:00Z",
      "year": 2017,
      "variant": "no_be",
      "smt": true,
      "side": "short",
      "pnl_pts": 3.0,
      "outcome": "win"
    },
    {
      "ts": "2017-01-10T15:00:00Z",
      "year": 2017,
      "variant": "be_50",
      "smt": true,
      "side": "short",
      "pnl_pts": 0.0,
      "outcome": "be"
    },
    {
      "ts": "2017-01-10T15:00:00Z",
      "year": 2017,
      "variant": "tp1_be",
      "smt": true,
      "side": "short",
      "pnl_pts": 0.75,
      "outcome": "win"
    },
    {
      "ts": "2017-05-09T14:00:00Z",
      "year": 2017,
      "variant": "no_be",
      "smt": true,
      "side": "short",
      "pnl_pts": -2.5,
      "outcome": "loss"
    },
    {
      "ts": "2017-05-09T14:00:00Z",
      "year": 2017,
      "variant": "be_50",
      "smt": true,
      "side": "short",
      "pnl_pts": -2.5,
      "outcome": "loss"
    },
    {
      "ts": "2017-05-09T14:00:00Z",
      "year": 2017,
      "variant": "tp1_be",
      "smt": true,
      "side": "short",
      "pnl_pts": -2.5,
      "outcome": "loss"
    },
    {
      "ts": "2017-09-12T14:00:00Z",
      "year": 2017,
      "variant": "no_be",
      "smt": true,
      "side": "long",
      "pnl_pts": 5.0,
      "outcome": "win"
    },
    {
      "ts": "2017-09-12T14:00:00Z",
      "year": 2017,
      "variant": "be_50",
      "smt": true,
      "side": "long",
      "pnl_pts": 0.0,
      "outcome": "be"
    },
    {
      "ts": "2017-09-12T14:00:00Z",
      "year": 2017,
      "variant": "tp1_be",
      "smt": true,
      "side": "long",
      "pnl_pts": 1.25,
      "outcome": "win"
    },
    {
      "ts": "2017-10-11T14:00:00Z",
      "year": 2017,
      "variant": "no_be",
      "smt": true,
      "side": "short",
      "pnl_pts": -5.5,
      "outcome": "loss"
    },
    {
      "ts": "2017-10-11T14:00:00Z",
      "year": 2017,
      "variant": "be_50",
      "smt": true,
      "side": "short",
      "pnl_pts": -5.5,
      "outcome": "loss"
    },
    {
      "ts": "2017-10-11T14:00:00Z",
      "year": 2017,
      "variant": "tp1_be",
      "smt": true,
      "side": "short",
      "pnl_pts": -5.5,
      "outcome": "loss"
    },
    {
      "ts": "2018-02-06T15:00:00Z",
      "year": 2018,
      "variant": "no_be",
      "smt": true,
      "side": "short",
      "pnl_pts": 32.75,
      "outcome": "win"
    },
    {
      "ts": "2018-02-06T15:00:00Z",
      "year": 2018,
      "variant": "be_50",
      "smt": true,
      "side": "short",
      "pnl_pts": 32.75,
      "outcome": "win"
    },
    {
      "ts": "2018-02-06T15:00:00Z",
      "year": 2018,
      "variant": "tp1_be",
      "smt": true,
      "side": "short",
      "pnl_pts": 24.5625,
      "outcome": "win"
    },
    {
      "ts": "2018-06-05T14:00:00Z",
      "year": 2018,
      "variant": "no_be",
      "smt": true,
      "side": "short",
      "pnl_pts": 5.25,
      "outcome": "win"
    },
    {
      "ts": "2018-06-05T14:00:00Z",
      "year": 2018,
      "variant": "be_50",
      "smt": true,
      "side": "short",
      "pnl_pts": 5.25,
      "outcome": "win"
    },
    {
      "ts": "2018-06-05T14:00:00Z",
      "year": 2018,
      "variant": "tp1_be",
      "smt": true,
      "side": "short",
      "pnl_pts": 3.9375,
      "outcome": "win"
    },
    {
      "ts": "2018-08-07T14:00:00Z",
      "year": 2018,
      "variant": "no_be",
      "smt": true,
      "side": "long",
      "pnl_pts": 5.25,
      "outcome": "win"
    },
    {
      "ts": "2018-08-07T14:00:00Z",
      "year": 2018,
      "variant": "be_50",
      "smt": true,
      "side": "long",
      "pnl_pts": 5.25,
      "outcome": "win"
    },
    {
      "ts": "2018-08-07T14:00:00Z",
      "year": 2018,
      "variant": "tp1_be",
      "smt": true,
      "side": "long",
      "pnl_pts": 3.9375,
      "outcome": "win"
    },
    {
      "ts": "2019-02-12T15:00:00Z",
      "year": 2019,
      "variant": "no_be",
      "smt": true,
      "side": "short",
      "pnl_pts": 8.5,
      "outcome": "win"
    },
    {
      "ts": "2019-02-12T15:00:00Z",
      "year": 2019,
      "variant": "be_50",
      "smt": true,
      "side": "short",
      "pnl_pts": 0.0,
      "outcome": "be"
    },
    {
      "ts": "2019-02-12T15:00:00Z",
      "year": 2019,
      "variant": "tp1_be",
      "smt": true,
      "side": "short",
      "pnl_pts": 2.125,
      "outcome": "win"
    },
    {
      "ts": "2019-05-07T14:00:00Z",
      "year": 2019,
      "variant": "no_be",
      "smt": false,
      "side": "long",
      "pnl_pts": 17.25,
      "outcome": "win"
    },
    {
      "ts": "2019-05-07T14:00:00Z",
      "year": 2019,
      "variant": "be_50",
      "smt": false,
      "side": "long",
      "pnl_pts": 0.0,
      "outcome": "be"
    },
    {
      "ts": "2019-05-07T14:00:00Z",
      "year": 2019,
      "variant": "tp1_be",
      "smt": false,
      "side": "long",
      "pnl_pts": 4.3125,
      "outcome": "win"
    },
    {
      "ts": "2019-06-10T14:00:00Z",
      "year": 2019,
      "variant": "no_be",
      "smt": true,
      "side": "short",
      "pnl_pts": -10.0,
      "outcome": "loss"
    },
    {
      "ts": "2019-06-10T14:00:00Z",
      "year": 2019,
      "variant": "be_50",
      "smt": true,
      "side": "short",
      "pnl_pts": -10.0,
      "outcome": "loss"
    },
    {
      "ts": "2019-06-10T14:00:00Z",
      "year": 2019,
      "variant": "tp1_be",
      "smt": true,
      "side": "short",
      "pnl_pts": -10.0,
      "outcome": "loss"
    },
    {
      "ts": "2019-07-09T14:00:00Z",
      "year": 2019,
      "variant": "no_be",
      "smt": true,
      "side": "short",
      "pnl_pts": -6.75,
      "outcome": "loss"
    },
    {
      "ts": "2019-07-09T14:00:00Z",
      "year": 2019,
      "variant": "be_50",
      "smt": true,
      "side": "short",
      "pnl_pts": -6.75,
      "outcome": "loss"
    },
    {
      "ts": "2019-07-09T14:00:00Z",
      "year": 2019,
      "variant": "tp1_be",
      "smt": true,
      "side": "short",
      "pnl_pts": -6.75,
      "outcome": "loss"
    },
    {
      "ts": "2019-10-09T14:00:00Z",
      "year": 2019,
      "variant": "no_be",
      "smt": true,
      "side": "short",
      "pnl_pts": 8.0,
      "outcome": "win"
    },
    {
      "ts": "2019-10-09T14:00:00Z",
      "year": 2019,
      "variant": "be_50",
      "smt": true,
      "side": "short",
      "pnl_pts": 8.0,
      "outcome": "win"
    },
    {
      "ts": "2019-10-09T14:00:00Z",
      "year": 2019,
      "variant": "tp1_be",
      "smt": true,
      "side": "short",
      "pnl_pts": 8.0,
      "outcome": "win"
    },
    {
      "ts": "2019-12-17T15:00:00Z",
      "year": 2019,
      "variant": "no_be",
      "smt": false,
      "side": "short",
      "pnl_pts": -5.5,
      "outcome": "loss"
    },
    {
      "ts": "2019-12-17T15:00:00Z",
      "year": 2019,
      "variant": "be_50",
      "smt": false,
      "side": "short",
      "pnl_pts": -5.5,
      "outcome": "loss"
    },
    {
      "ts": "2019-12-17T15:00:00Z",
      "year": 2019,
      "variant": "tp1_be",
      "smt": false,
      "side": "short",
      "pnl_pts": -5.5,
      "outcome": "loss"
    },
    {
      "ts": "2020-02-11T15:00:00Z",
      "year": 2020,
      "variant": "no_be",
      "smt": true,
      "side": "short",
      "pnl_pts": -7.75,
      "outcome": "loss"
    },
    {
      "ts": "2020-02-11T15:00:00Z",
      "year": 2020,
      "variant": "be_50",
      "smt": true,
      "side": "short",
      "pnl_pts": -7.75,
      "outcome": "loss"
    },
    {
      "ts": "2020-02-11T15:00:00Z",
      "year": 2020,
      "variant": "tp1_be",
      "smt": true,
      "side": "short",
      "pnl_pts": -7.75,
      "outcome": "loss"
    },
    {
      "ts": "2020-03-17T14:00:00Z",
      "year": 2020,
      "variant": "no_be",
      "smt": false,
      "side": "short",
      "pnl_pts": -52.0,
      "outcome": "loss"
    },
    {
      "ts": "2020-03-17T14:00:00Z",
      "year": 2020,
      "variant": "be_50",
      "smt": false,
      "side": "short",
      "pnl_pts": -52.0,
      "outcome": "loss"
    },
    {
      "ts": "2020-03-17T14:00:00Z",
      "year": 2020,
      "variant": "tp1_be",
      "smt": false,
      "side": "short",
      "pnl_pts": -52.0,
      "outcome": "loss"
    },
    {
      "ts": "2020-04-07T14:00:00Z",
      "year": 2020,
      "variant": "no_be",
      "smt": false,
      "side": "long",
      "pnl_pts": -25.5,
      "outcome": "loss"
    },
    {
      "ts": "2020-04-07T14:00:00Z",
      "year": 2020,
      "variant": "be_50",
      "smt": false,
      "side": "long",
      "pnl_pts": -25.5,
      "outcome": "loss"
    },
    {
      "ts": "2020-04-07T14:00:00Z",
      "year": 2020,
      "variant": "tp1_be",
      "smt": false,
      "side": "long",
      "pnl_pts": -25.5,
      "outcome": "loss"
    },
    {
      "ts": "2020-07-07T14:00:00Z",
      "year": 2020,
      "variant": "no_be",
      "smt": true,
      "side": "short",
      "pnl_pts": -18.25,
      "outcome": "loss"
    },
    {
      "ts": "2020-07-07T14:00:00Z",
      "year": 2020,
      "variant": "be_50",
      "smt": true,
      "side": "short",
      "pnl_pts": -18.25,
      "outcome": "loss"
    },
    {
      "ts": "2020-07-07T14:00:00Z",
      "year": 2020,
      "variant": "tp1_be",
      "smt": true,
      "side": "short",
      "pnl_pts": -18.25,
      "outcome": "loss"
    },
    {
      "ts": "2020-08-10T14:00:00Z",
      "year": 2020,
      "variant": "no_be",
      "smt": true,
      "side": "long",
      "pnl_pts": -14.25,
      "outcome": "loss"
    },
    {
      "ts": "2020-08-10T14:00:00Z",
      "year": 2020,
      "variant": "be_50",
      "smt": true,
      "side": "long",
      "pnl_pts": -14.25,
      "outcome": "loss"
    },
    {
      "ts": "2020-08-10T14:00:00Z",
      "year": 2020,
      "variant": "tp1_be",
      "smt": true,
      "side": "long",
      "pnl_pts": -14.25,
      "outcome": "loss"
    },
    {
      "ts": "2020-10-06T14:00:00Z",
      "year": 2020,
      "variant": "no_be",
      "smt": true,
      "side": "short",
      "pnl_pts": -12.25,
      "outcome": "loss"
    },
    {
      "ts": "2020-10-06T14:00:00Z",
      "year": 2020,
      "variant": "be_50",
      "smt": true,
      "side": "short",
      "pnl_pts": -12.25,
      "outcome": "loss"
    },
    {
      "ts": "2020-10-06T14:00:00Z",
      "year": 2020,
      "variant": "tp1_be",
      "smt": true,
      "side": "short",
      "pnl_pts": -12.25,
      "outcome": "loss"
    },
    {
      "ts": "2020-12-09T15:00:00Z",
      "year": 2020,
      "variant": "no_be",
      "smt": false,
      "side": "long",
      "pnl_pts": -38.25,
      "outcome": "loss"
    },
    {
      "ts": "2020-12-09T15:00:00Z",
      "year": 2020,
      "variant": "be_50",
      "smt": false,
      "side": "long",
      "pnl_pts": 0.0,
      "outcome": "be"
    },
    {
      "ts": "2020-12-09T15:00:00Z",
      "year": 2020,
      "variant": "tp1_be",
      "smt": false,
      "side": "long",
      "pnl_pts": 8.25,
      "outcome": "win"
    },
    {
      "ts": "2021-02-09T15:00:00Z",
      "year": 2021,
      "variant": "no_be",
      "smt": true,
      "side": "short",
      "pnl_pts": 17.0,
      "outcome": "win"
    },
    {
      "ts": "2021-02-09T15:00:00Z",
      "year": 2021,
      "variant": "be_50",
      "smt": true,
      "side": "short",
      "pnl_pts": 17.0,
      "outcome": "win"
    },
    {
      "ts": "2021-02-09T15:00:00Z",
      "year": 2021,
      "variant": "tp1_be",
      "smt": true,
      "side": "short",
      "pnl_pts": 12.75,
      "outcome": "win"
    },
    {
      "ts": "2021-07-07T14:00:00Z",
      "year": 2021,
      "variant": "no_be",
      "smt": true,
      "side": "long",
      "pnl_pts": 11.25,
      "outcome": "win"
    },
    {
      "ts": "2021-07-07T14:00:00Z",
      "year": 2021,
      "variant": "be_50",
      "smt": true,
      "side": "long",
      "pnl_pts": 11.25,
      "outcome": "win"
    },
    {
      "ts": "2021-07-07T14:00:00Z",
      "year": 2021,
      "variant": "tp1_be",
      "smt": true,
      "side": "long",
      "pnl_pts": 11.25,
      "outcome": "win"
    },
    {
      "ts": "2021-08-09T14:00:00Z",
      "year": 2021,
      "variant": "no_be",
      "smt": true,
      "side": "long",
      "pnl_pts": 16.5,
      "outcome": "win"
    },
    {
      "ts": "2021-08-09T14:00:00Z",
      "year": 2021,
      "variant": "be_50",
      "smt": true,
      "side": "long",
      "pnl_pts": 16.5,
      "outcome": "win"
    },
    {
      "ts": "2021-08-09T14:00:00Z",
      "year": 2021,
      "variant": "tp1_be",
      "smt": true,
      "side": "long",
      "pnl_pts": 16.5,
      "outcome": "win"
    },
    {
      "ts": "2021-10-12T14:00:00Z",
      "year": 2021,
      "variant": "no_be",
      "smt": true,
      "side": "short",
      "pnl_pts": -30.75,
      "outcome": "loss"
    },
    {
      "ts": "2021-10-12T14:00:00Z",
      "year": 2021,
      "variant": "be_50",
      "smt": true,
      "side": "short",
      "pnl_pts": 0.0,
      "outcome": "be"
    },
    {
      "ts": "2021-10-12T14:00:00Z",
      "year": 2021,
      "variant": "tp1_be",
      "smt": true,
      "side": "short",
      "pnl_pts": 6.8125,
      "outcome": "win"
    },
    {
      "ts": "2021-11-12T15:00:00Z",
      "year": 2021,
      "variant": "no_be",
      "smt": true,
      "side": "short",
      "pnl_pts": -12.75,
      "outcome": "loss"
    },
    {
      "ts": "2021-11-12T15:00:00Z",
      "year": 2021,
      "variant": "be_50",
      "smt": true,
      "side": "short",
      "pnl_pts": -12.75,
      "outcome": "loss"
    },
    {
      "ts": "2021-11-12T15:00:00Z",
      "year": 2021,
      "variant": "tp1_be",
      "smt": true,
      "side": "short",
      "pnl_pts": -12.75,
      "outcome": "loss"
    },
    {
      "ts": "2022-01-04T15:00:00Z",
      "year": 2022,
      "variant": "no_be",
      "smt": true,
      "side": "long",
      "pnl_pts": -20.5,
      "outcome": "loss"
    },
    {
      "ts": "2022-01-04T15:00:00Z",
      "year": 2022,
      "variant": "be_50",
      "smt": true,
      "side": "long",
      "pnl_pts": -20.5,
      "outcome": "loss"
    },
    {
      "ts": "2022-01-04T15:00:00Z",
      "year": 2022,
      "variant": "tp1_be",
      "smt": true,
      "side": "long",
      "pnl_pts": -20.5,
      "outcome": "loss"
    },
    {
      "ts": "2022-03-09T15:00:00Z",
      "year": 2022,
      "variant": "no_be",
      "smt": false,
      "side": "short",
      "pnl_pts": -38.75,
      "outcome": "loss"
    },
    {
      "ts": "2022-03-09T15:00:00Z",
      "year": 2022,
      "variant": "be_50",
      "smt": false,
      "side": "short",
      "pnl_pts": -38.75,
      "outcome": "loss"
    },
    {
      "ts": "2022-03-09T15:00:00Z",
      "year": 2022,
      "variant": "tp1_be",
      "smt": false,
      "side": "short",
      "pnl_pts": -38.75,
      "outcome": "loss"
    },
    {
      "ts": "2022-06-01T14:00:00Z",
      "year": 2022,
      "variant": "no_be",
      "smt": false,
      "side": "long",
      "pnl_pts": -43.25,
      "outcome": "loss"
    },
    {
      "ts": "2022-06-01T14:00:00Z",
      "year": 2022,
      "variant": "be_50",
      "smt": false,
      "side": "long",
      "pnl_pts": -43.25,
      "outcome": "loss"
    },
    {
      "ts": "2022-06-01T14:00:00Z",
      "year": 2022,
      "variant": "tp1_be",
      "smt": false,
      "side": "long",
      "pnl_pts": -43.25,
      "outcome": "loss"
    },
    {
      "ts": "2022-10-04T14:00:00Z",
      "year": 2022,
      "variant": "no_be",
      "smt": true,
      "side": "short",
      "pnl_pts": -22.5,
      "outcome": "loss"
    },
    {
      "ts": "2022-10-04T14:00:00Z",
      "year": 2022,
      "variant": "be_50",
      "smt": true,
      "side": "short",
      "pnl_pts": 0.0,
      "outcome": "be"
    },
    {
      "ts": "2022-10-04T14:00:00Z",
      "year": 2022,
      "variant": "tp1_be",
      "smt": true,
      "side": "short",
      "pnl_pts": 7.125,
      "outcome": "win"
    },
    {
      "ts": "2022-11-01T14:00:00Z",
      "year": 2022,
      "variant": "no_be",
      "smt": false,
      "side": "long",
      "pnl_pts": -54.0,
      "outcome": "loss"
    },
    {
      "ts": "2022-11-01T14:00:00Z",
      "year": 2022,
      "variant": "be_50",
      "smt": false,
      "side": "long",
      "pnl_pts": -54.0,
      "outcome": "loss"
    },
    {
      "ts": "2022-11-01T14:00:00Z",
      "year": 2022,
      "variant": "tp1_be",
      "smt": false,
      "side": "long",
      "pnl_pts": -54.0,
      "outcome": "loss"
    },
    {
      "ts": "2023-02-01T15:00:00Z",
      "year": 2023,
      "variant": "no_be",
      "smt": false,
      "side": "long",
      "pnl_pts": -24.25,
      "outcome": "loss"
    },
    {
      "ts": "2023-02-01T15:00:00Z",
      "year": 2023,
      "variant": "be_50",
      "smt": false,
      "side": "long",
      "pnl_pts": 0.0,
      "outcome": "be"
    },
    {
      "ts": "2023-02-01T15:00:00Z",
      "year": 2023,
      "variant": "tp1_be",
      "smt": false,
      "side": "long",
      "pnl_pts": 6.125,
      "outcome": "win"
    },
    {
      "ts": "2023-04-04T14:00:00Z",
      "year": 2023,
      "variant": "no_be",
      "smt": true,
      "side": "short",
      "pnl_pts": 26.0,
      "outcome": "win"
    },
    {
      "ts": "2023-04-04T14:00:00Z",
      "year": 2023,
      "variant": "be_50",
      "smt": true,
      "side": "short",
      "pnl_pts": 26.0,
      "outcome": "win"
    },
    {
      "ts": "2023-04-04T14:00:00Z",
      "year": 2023,
      "variant": "tp1_be",
      "smt": true,
      "side": "short",
      "pnl_pts": 19.5,
      "outcome": "win"
    },
    {
      "ts": "2023-05-02T14:00:00Z",
      "year": 2023,
      "variant": "no_be",
      "smt": false,
      "side": "long",
      "pnl_pts": -24.25,
      "outcome": "loss"
    },
    {
      "ts": "2023-05-02T14:00:00Z",
      "year": 2023,
      "variant": "be_50",
      "smt": false,
      "side": "long",
      "pnl_pts": -24.25,
      "outcome": "loss"
    },
    {
      "ts": "2023-05-02T14:00:00Z",
      "year": 2023,
      "variant": "tp1_be",
      "smt": false,
      "side": "long",
      "pnl_pts": -24.25,
      "outcome": "loss"
    },
    {
      "ts": "2023-07-06T14:00:00Z",
      "year": 2023,
      "variant": "no_be",
      "smt": false,
      "side": "long",
      "pnl_pts": 19.0,
      "outcome": "win"
    },
    {
      "ts": "2023-07-06T14:00:00Z",
      "year": 2023,
      "variant": "be_50",
      "smt": false,
      "side": "long",
      "pnl_pts": 0.0,
      "outcome": "be"
    },
    {
      "ts": "2023-07-06T14:00:00Z",
      "year": 2023,
      "variant": "tp1_be",
      "smt": false,
      "side": "long",
      "pnl_pts": 4.75,
      "outcome": "win"
    },
    {
      "ts": "2023-08-29T14:00:00Z",
      "year": 2023,
      "variant": "no_be",
      "smt": true,
      "side": "short",
      "pnl_pts": -26.75,
      "outcome": "loss"
    },
    {
      "ts": "2023-08-29T14:00:00Z",
      "year": 2023,
      "variant": "be_50",
      "smt": true,
      "side": "short",
      "pnl_pts": -26.75,
      "outcome": "loss"
    },
    {
      "ts": "2023-08-29T14:00:00Z",
      "year": 2023,
      "variant": "tp1_be",
      "smt": true,
      "side": "short",
      "pnl_pts": -26.75,
      "outcome": "loss"
    },
    {
      "ts": "2023-10-03T14:00:00Z",
      "year": 2023,
      "variant": "no_be",
      "smt": false,
      "side": "long",
      "pnl_pts": -28.0,
      "outcome": "loss"
    },
    {
      "ts": "2023-10-03T14:00:00Z",
      "year": 2023,
      "variant": "be_50",
      "smt": false,
      "side": "long",
      "pnl_pts": -28.0,
      "outcome": "loss"
    },
    {
      "ts": "2023-10-03T14:00:00Z",
      "year": 2023,
      "variant": "tp1_be",
      "smt": false,
      "side": "long",
      "pnl_pts": -28.0,
      "outcome": "loss"
    },
    {
      "ts": "2023-12-05T15:00:00Z",
      "year": 2023,
      "variant": "no_be",
      "smt": true,
      "side": "short",
      "pnl_pts": -42.25,
      "outcome": "loss"
    },
    {
      "ts": "2023-12-05T15:00:00Z",
      "year": 2023,
      "variant": "be_50",
      "smt": true,
      "side": "short",
      "pnl_pts": 0.0,
      "outcome": "be"
    },
    {
      "ts": "2023-12-05T15:00:00Z",
      "year": 2023,
      "variant": "tp1_be",
      "smt": true,
      "side": "short",
      "pnl_pts": 11.5625,
      "outcome": "win"
    },
    {
      "ts": "2024-01-03T15:00:00Z",
      "year": 2024,
      "variant": "no_be",
      "smt": false,
      "side": "long",
      "pnl_pts": -8.25,
      "outcome": "loss"
    },
    {
      "ts": "2024-01-03T15:00:00Z",
      "year": 2024,
      "variant": "be_50",
      "smt": false,
      "side": "long",
      "pnl_pts": -8.25,
      "outcome": "loss"
    },
    {
      "ts": "2024-01-03T15:00:00Z",
      "year": 2024,
      "variant": "tp1_be",
      "smt": false,
      "side": "long",
      "pnl_pts": -8.25,
      "outcome": "loss"
    },
    {
      "ts": "2024-01-30T15:00:00Z",
      "year": 2024,
      "variant": "no_be",
      "smt": true,
      "side": "long",
      "pnl_pts": -35.5,
      "outcome": "loss"
    },
    {
      "ts": "2024-01-30T15:00:00Z",
      "year": 2024,
      "variant": "be_50",
      "smt": true,
      "side": "long",
      "pnl_pts": 0.0,
      "outcome": "be"
    },
    {
      "ts": "2024-01-30T15:00:00Z",
      "year": 2024,
      "variant": "tp1_be",
      "smt": true,
      "side": "long",
      "pnl_pts": 5.125,
      "outcome": "win"
    },
    {
      "ts": "2024-03-06T15:00:00Z",
      "year": 2024,
      "variant": "no_be",
      "smt": true,
      "side": "long",
      "pnl_pts": 47.25,
      "outcome": "win"
    },
    {
      "ts": "2024-03-06T15:00:00Z",
      "year": 2024,
      "variant": "be_50",
      "smt": true,
      "side": "long",
      "pnl_pts": 0.0,
      "outcome": "be"
    },
    {
      "ts": "2024-03-06T15:00:00Z",
      "year": 2024,
      "variant": "tp1_be",
      "smt": true,
      "side": "long",
      "pnl_pts": 11.8125,
      "outcome": "win"
    },
    {
      "ts": "2024-09-04T14:00:00Z",
      "year": 2024,
      "variant": "no_be",
      "smt": false,
      "side": "short",
      "pnl_pts": 32.5,
      "outcome": "timeout"
    },
    {
      "ts": "2024-09-04T14:00:00Z",
      "year": 2024,
      "variant": "be_50",
      "smt": false,
      "side": "short",
      "pnl_pts": 32.5,
      "outcome": "timeout"
    },
    {
      "ts": "2024-09-04T14:00:00Z",
      "year": 2024,
      "variant": "tp1_be",
      "smt": false,
      "side": "short",
      "pnl_pts": 32.5,
      "outcome": "timeout"
    },
    {
      "ts": "2024-10-01T14:00:00Z",
      "year": 2024,
      "variant": "no_be",
      "smt": true,
      "side": "long",
      "pnl_pts": -44.0,
      "outcome": "loss"
    },
    {
      "ts": "2024-10-01T14:00:00Z",
      "year": 2024,
      "variant": "be_50",
      "smt": true,
      "side": "long",
      "pnl_pts": -44.0,
      "outcome": "loss"
    },
    {
      "ts": "2024-10-01T14:00:00Z",
      "year": 2024,
      "variant": "tp1_be",
      "smt": true,
      "side": "long",
      "pnl_pts": -44.0,
      "outcome": "loss"
    },
    {
      "ts": "2024-10-29T14:00:00Z",
      "year": 2024,
      "variant": "no_be",
      "smt": false,
      "side": "short",
      "pnl_pts": -61.25,
      "outcome": "loss"
    },
    {
      "ts": "2024-10-29T14:00:00Z",
      "year": 2024,
      "variant": "be_50",
      "smt": false,
      "side": "short",
      "pnl_pts": -61.25,
      "outcome": "loss"
    },
    {
      "ts": "2024-10-29T14:00:00Z",
      "year": 2024,
      "variant": "tp1_be",
      "smt": false,
      "side": "short",
      "pnl_pts": -61.25,
      "outcome": "loss"
    },
    {
      "ts": "2024-12-03T15:00:00Z",
      "year": 2024,
      "variant": "no_be",
      "smt": true,
      "side": "short",
      "pnl_pts": 15.25,
      "outcome": "win"
    },
    {
      "ts": "2024-12-03T15:00:00Z",
      "year": 2024,
      "variant": "be_50",
      "smt": true,
      "side": "short",
      "pnl_pts": 0.0,
      "outcome": "be"
    },
    {
      "ts": "2024-12-03T15:00:00Z",
      "year": 2024,
      "variant": "tp1_be",
      "smt": true,
      "side": "short",
      "pnl_pts": 3.8125,
      "outcome": "win"
    }
  ]
}