{
 "meta": {
  "asset": "SI",
  "window1": "09:30-10:00 ET",
  "window2": "10:00-11:00 ET",
  "dateFrom": "2016-01-03",
  "dateTo": "2026-05-11",
  "n_days": 2533,
  "point_value_usd": 5000
 },
 "continuation": {
  "continuation_rate": 50.18,
  "reversal_rate": 49.82,
  "avg_move1": -0.0051,
  "avg_move2": -0.0056,
  "avg_move2_continuation": -0.0139,
  "avg_move2_reversal": 0.0027,
  "by_year": [
   {
    "year": 2016,
    "n": 241,
    "continuation_rate": 46.06
   },
   {
    "year": 2017,
    "n": 236,
    "continuation_rate": 46.61
   },
   {
    "year": 2018,
    "n": 236,
    "continuation_rate": 52.12
   },
   {
    "year": 2019,
    "n": 237,
    "continuation_rate": 48.52
   },
   {
    "year": 2020,
    "n": 245,
    "continuation_rate": 48.57
   },
   {
    "year": 2021,
    "n": 254,
    "continuation_rate": 51.57
   },
   {
    "year": 2022,
    "n": 252,
    "continuation_rate": 55.95
   },
   {
    "year": 2023,
    "n": 246,
    "continuation_rate": 48.37
   },
   {
    "year": 2024,
    "n": 249,
    "continuation_rate": 53.01
   },
   {
    "year": 2025,
    "n": 247,
    "continuation_rate": 50.61
   },
   {
    "year": 2026,
    "n": 90,
    "continuation_rate": 50.0
   }
  ],
  "by_regime": {
   "full": {
    "n_days": 2533,
    "continuation_rate": 50.18
   },
   "2024+": {
    "n_days": 586,
    "continuation_rate": 51.54
   },
   "2025+": {
    "n_days": 337,
    "continuation_rate": 50.45
   },
   "2026": {
    "n_days": 90,
    "continuation_rate": 50.0
   }
  },
  "manip": {
   "n_days": 1158,
   "continuation_rate": 50.0
  }
 }
}