{
  "asset": "YM",
  "examples": [
    {
      "date": "2024-08-06",
      "side": "long",
      "level": "AsiaLo",
      "level_price": 38988.0,
      "entry_ts": "2024-08-06T10:00:00-04:00",
      "entry_price": 39141.0,
      "sl_price": 38760.0,
      "tp1R_price": 39522.0,
      "pnl_pts": 176.0,
      "outcome": "win",
      "manip_window": {
        "start_ts": "2024-08-06T09:30:00-04:00",
        "end_ts": "2024-08-06T09:59:00-04:00"
      },
      "trade_window": {
        "start_ts": "2024-08-06T10:00:00-04:00",
        "end_ts": "2024-08-06T10:59:00-04:00"
      },
      "bars": [
        {
          "ts": "2024-08-06T09:25:00-04:00",
          "o": 38910.0,
          "h": 38933.0,
          "l": 38907.0,
          "c": 38925.0
        },
        {
          "ts": "2024-08-06T09:26:00-04:00",
          "o": 38929.0,
          "h": 38950.0,
          "l": 38929.0,
          "c": 38939.0
        },
        {
          "ts": "2024-08-06T09:27:00-04:00",
          "o": 38939.0,
          "h": 38940.0,
          "l": 38925.0,
          "c": 38934.0
        },
        {
          "ts": "2024-08-06T09:28:00-04:00",
          "o": 38930.0,
          "h": 38931.0,
          "l": 38878.0,
          "c": 38926.0
        },
        {
          "ts": "2024-08-06T09:29:00-04:00",
          "o": 38925.0,
          "h": 38927.0,
          "l": 38845.0,
          "c": 38876.0
        },
        {
          "ts": "2024-08-06T09:30:00-04:00",
          "o": 38880.0,
          "h": 38932.0,
          "l": 38772.0,
          "c": 38796.0
        },
        {
          "ts": "2024-08-06T09:31:00-04:00",
          "o": 38797.0,
          "h": 38825.0,
          "l": 38760.0,
          "c": 38816.0
        },
        {
          "ts": "2024-08-06T09:32:00-04:00",
          "o": 38816.0,
          "h": 38916.0,
          "l": 38810.0,
          "c": 38882.0
        },
        {
          "ts": "2024-08-06T09:33:00-04:00",
          "o": 38883.0,
          "h": 38895.0,
          "l": 38828.0,
          "c": 38854.0
        },
        {
          "ts": "2024-08-06T09:34:00-04:00",
          "o": 38851.0,
          "h": 38879.0,
          "l": 38824.0,
          "c": 38861.0
        },
        {
          "ts": "2024-08-06T09:35:00-04:00",
          "o": 38864.0,
          "h": 38878.0,
          "l": 38848.0,
          "c": 38875.0
        },
        {
          "ts": "2024-08-06T09:36:00-04:00",
          "o": 38876.0,
          "h": 38926.0,
          "l": 38848.0,
          "c": 38919.0
        },
        {
          "ts": "2024-08-06T09:37:00-04:00",
          "o": 38917.0,
          "h": 38972.0,
          "l": 38914.0,
          "c": 38943.0
        },
        {
          "ts": "2024-08-06T09:38:00-04:00",
          "o": 38940.0,
          "h": 38952.0,
          "l": 38922.0,
          "c": 38941.0
        },
        {
          "ts": "2024-08-06T09:39:00-04:00",
          "o": 38936.0,
          "h": 38972.0,
          "l": 38926.0,
          "c": 38945.0
        },
        {
          "ts": "2024-08-06T09:40:00-04:00",
          "o": 38945.0,
          "h": 38958.0,
          "l": 38906.0,
          "c": 38932.0
        },
        {
          "ts": "2024-08-06T09:41:00-04:00",
          "o": 38932.0,
          "h": 38940.0,
          "l": 38868.0,
          "c": 38915.0
        },
        {
          "ts": "2024-08-06T09:42:00-04:00",
          "o": 38921.0,
          "h": 38952.0,
          "l": 38896.0,
          "c": 38898.0
        },
        {
          "ts": "2024-08-06T09:43:00-04:00",
          "o": 38899.0,
          "h": 38915.0,
          "l": 38883.0,
          "c": 38897.0
        },
        {
          "ts": "2024-08-06T09:44:00-04:00",
          "o": 38898.0,
          "h": 38955.0,
          "l": 38889.0,
          "c": 38939.0
        },
        {
          "ts": "2024-08-06T09:45:00-04:00",
          "o": 38938.0,
          "h": 38962.0,
          "l": 38903.0,
          "c": 38903.0
        },
        {
          "ts": "2024-08-06T09:46:00-04:00",
          "o": 38904.0,
          "h": 38947.0,
          "l": 38888.0,
          "c": 38944.0
        },
        {
          "ts": "2024-08-06T09:47:00-04:00",
          "o": 38947.0,
          "h": 38992.0,
          "l": 38944.0,
          "c": 38988.0
        },
        {
          "ts": "2024-08-06T09:48:00-04:00",
          "o": 38989.0,
          "h": 39004.0,
          "l": 38974.0,
          "c": 39004.0
        },
        {
          "ts": "2024-08-06T09:49:00-04:00",
          "o": 39004.0,
          "h": 39025.0,
          "l": 38966.0,
          "c": 39003.0
        },
        {
          "ts": "2024-08-06T09:50:00-04:00",
          "o": 39001.0,
          "h": 39039.0,
          "l": 38989.0,
          "c": 39037.0
        },
        {
          "ts": "2024-08-06T09:51:00-04:00",
          "o": 39040.0,
          "h": 39069.0,
          "l": 39024.0,
          "c": 39061.0
        },
        {
          "ts": "2024-08-06T09:52:00-04:00",
          "o": 39063.0,
          "h": 39102.0,
          "l": 39062.0,
          "c": 39099.0
        },
        {
          "ts": "2024-08-06T09:53:00-04:00",
          "o": 39098.0,
          "h": 39145.0,
          "l": 39091.0,
          "c": 39111.0
        },
        {
          "ts": "2024-08-06T09:54:00-04:00",
          "o": 39112.0,
          "h": 39148.0,
          "l": 39101.0,
          "c": 39125.0
        },
        {
          "ts": "2024-08-06T09:55:00-04:00",
          "o": 39125.0,
          "h": 39146.0,
          "l": 39109.0,
          "c": 39132.0
        },
        {
          "ts": "2024-08-06T09:56:00-04:00",
          "o": 39136.0,
          "h": 39163.0,
          "l": 39128.0,
          "c": 39156.0
        },
        {
          "ts": "2024-08-06T09:57:00-04:00",
          "o": 39153.0,
          "h": 39169.0,
          "l": 39135.0,
          "c": 39147.0
        },
        {
          "ts": "2024-08-06T09:58:00-04:00",
          "o": 39146.0,
          "h": 39153.0,
          "l": 39111.0,
          "c": 39128.0
        },
        {
          "ts": "2024-08-06T09:59:00-04:00",
          "o": 39130.0,
          "h": 39141.0,
          "l": 39111.0,
          "c": 39139.0
        },
        {
          "ts": "2024-08-06T10:00:00-04:00",
          "o": 39141.0,
          "h": 39160.0,
          "l": 39102.0,
          "c": 39146.0
        },
        {
          "ts": "2024-08-06T10:01:00-04:00",
          "o": 39150.0,
          "h": 39176.0,
          "l": 39134.0,
          "c": 39164.0
        },
        {
          "ts": "2024-08-06T10:02:00-04:00",
          "o": 39166.0,
          "h": 39194.0,
          "l": 39163.0,
          "c": 39190.0
        },
        {
          "ts": "2024-08-06T10:03:00-04:00",
          "o": 39190.0,
          "h": 39194.0,
          "l": 39167.0,
          "c": 39179.0
        },
        {
          "ts": "2024-08-06T10:04:00-04:00",
          "o": 39180.0,
          "h": 39186.0,
          "l": 39149.0,
          "c": 39173.0
        },
        {
          "ts": "2024-08-06T10:05:00-04:00",
          "o": 39171.0,
          "h": 39199.0,
          "l": 39156.0,
          "c": 39195.0
        },
        {
          "ts": "2024-08-06T10:06:00-04:00",
          "o": 39195.0,
          "h": 39195.0,
          "l": 39150.0,
          "c": 39186.0
        },
        {
          "ts": "2024-08-06T10:07:00-04:00",
          "o": 39181.0,
          "h": 39197.0,
          "l": 39165.0,
          "c": 39196.0
        },
        {
          "ts": "2024-08-06T10:08:00-04:00",
          "o": 39193.0,
          "h": 39223.0,
          "l": 39170.0,
          "c": 39216.0
        },
        {
          "ts": "2024-08-06T10:09:00-04:00",
          "o": 39215.0,
          "h": 39249.0,
          "l": 39215.0,
          "c": 39246.0
        },
        {
          "ts": "2024-08-06T10:10:00-04:00",
          "o": 39246.0,
          "h": 39254.0,
          "l": 39198.0,
          "c": 39209.0
        },
        {
          "ts": "2024-08-06T10:11:00-04:00",
          "o": 39209.0,
          "h": 39209.0,
          "l": 39184.0,
          "c": 39201.0
        },
        {
          "ts": "2024-08-06T10:12:00-04:00",
          "o": 39202.0,
          "h": 39216.0,
          "l": 39190.0,
          "c": 39210.0
        },
        {
          "ts": "2024-08-06T10:13:00-04:00",
          "o": 39211.0,
          "h": 39247.0,
          "l": 39204.0,
          "c": 39240.0
        },
        {
          "ts": "2024-08-06T10:14:00-04:00",
          "o": 39239.0,
          "h": 39243.0,
          "l": 39182.0,
          "c": 39201.0
        },
        {
          "ts": "2024-08-06T10:15:00-04:00",
          "o": 39201.0,
          "h": 39217.0,
          "l": 39162.0,
          "c": 39176.0
        },
        {
          "ts": "2024-08-06T10:16:00-04:00",
          "o": 39178.0,
          "h": 39225.0,
          "l": 39176.0,
          "c": 39225.0
        },
        {
          "ts": "2024-08-06T10:17:00-04:00",
          "o": 39224.0,
          "h": 39225.0,
          "l": 39179.0,
          "c": 39186.0
        },
        {
          "ts": "2024-08-06T10:18:00-04:00",
          "o": 39187.0,
          "h": 39220.0,
          "l": 39182.0,
          "c": 39220.0
        },
        {
          "ts": "2024-08-06T10:19:00-04:00",
          "o": 39221.0,
          "h": 39228.0,
          "l": 39189.0,
          "c": 39203.0
        },
        {
          "ts": "2024-08-06T10:20:00-04:00",
          "o": 39203.0,
          "h": 39216.0,
          "l": 39189.0,
          "c": 39213.0
        },
        {
          "ts": "2024-08-06T10:21:00-04:00",
          "o": 39212.0,
          "h": 39239.0,
          "l": 39200.0,
          "c": 39208.0
        },
        {
          "ts": "2024-08-06T10:22:00-04:00",
          "o": 39210.0,
          "h": 39218.0,
          "l": 39201.0,
          "c": 39211.0
        },
        {
          "ts": "2024-08-06T10:23:00-04:00",
          "o": 39210.0,
          "h": 39213.0,
          "l": 39190.0,
          "c": 39202.0
        },
        {
          "ts": "2024-08-06T10:24:00-04:00",
          "o": 39199.0,
          "h": 39252.0,
          "l": 39198.0,
          "c": 39249.0
        },
        {
          "ts": "2024-08-06T10:25:00-04:00",
          "o": 39249.0,
          "h": 39287.0,
          "l": 39243.0,
          "c": 39283.0
        },
        {
          "ts": "2024-08-06T10:26:00-04:00",
          "o": 39281.0,
          "h": 39283.0,
          "l": 39261.0,
          "c": 39267.0
        },
        {
          "ts": "2024-08-06T10:27:00-04:00",
          "o": 39268.0,
          "h": 39280.0,
          "l": 39244.0,
          "c": 39262.0
        },
        {
          "ts": "2024-08-06T10:28:00-04:00",
          "o": 39262.0,
          "h": 39282.0,
          "l": 39255.0,
          "c": 39259.0
        },
        {
          "ts": "2024-08-06T10:29:00-04:00",
          "o": 39258.0,
          "h": 39265.0,
          "l": 39175.0,
          "c": 39185.0
        },
        {
          "ts": "2024-08-06T10:30:00-04:00",
          "o": 39187.0,
          "h": 39193.0,
          "l": 39134.0,
          "c": 39156.0
        },
        {
          "ts": "2024-08-06T10:31:00-04:00",
          "o": 39155.0,
          "h": 39182.0,
          "l": 39150.0,
          "c": 39156.0
        },
        {
          "ts": "2024-08-06T10:32:00-04:00",
          "o": 39156.0,
          "h": 39179.0,
          "l": 39143.0,
          "c": 39175.0
        },
        {
          "ts": "2024-08-06T10:33:00-04:00",
          "o": 39173.0,
          "h": 39190.0,
          "l": 39144.0,
          "c": 39169.0
        },
        {
          "ts": "2024-08-06T10:34:00-04:00",
          "o": 39168.0,
          "h": 39217.0,
          "l": 39159.0,
          "c": 39217.0
        },
        {
          "ts": "2024-08-06T10:35:00-04:00",
          "o": 39214.0,
          "h": 39244.0,
          "l": 39203.0,
          "c": 39242.0
        },
        {
          "ts": "2024-08-06T10:36:00-04:00",
          "o": 39240.0,
          "h": 39251.0,
          "l": 39224.0,
          "c": 39245.0
        },
        {
          "ts": "2024-08-06T10:37:00-04:00",
          "o": 39242.0,
          "h": 39294.0,
          "l": 39235.0,
          "c": 39291.0
        },
        {
          "ts": "2024-08-06T10:38:00-04:00",
          "o": 39293.0,
          "h": 39299.0,
          "l": 39258.0,
          "c": 39260.0
        },
        {
          "ts": "2024-08-06T10:39:00-04:00",
          "o": 39259.0,
          "h": 39265.0,
          "l": 39217.0,
          "c": 39242.0
        },
        {
          "ts": "2024-08-06T10:40:00-04:00",
          "o": 39241.0,
          "h": 39274.0,
          "l": 39233.0,
          "c": 39261.0
        },
        {
          "ts": "2024-08-06T10:41:00-04:00",
          "o": 39259.0,
          "h": 39271.0,
          "l": 39237.0,
          "c": 39268.0
        },
        {
          "ts": "2024-08-06T10:42:00-04:00",
          "o": 39267.0,
          "h": 39278.0,
          "l": 39254.0,
          "c": 39274.0
        },
        {
          "ts": "2024-08-06T10:43:00-04:00",
          "o": 39275.0,
          "h": 39291.0,
          "l": 39263.0,
          "c": 39270.0
        },
        {
          "ts": "2024-08-06T10:44:00-04:00",
          "o": 39267.0,
          "h": 39289.0,
          "l": 39264.0,
          "c": 39287.0
        },
        {
          "ts": "2024-08-06T10:45:00-04:00",
          "o": 39283.0,
          "h": 39299.0,
          "l": 39270.0,
          "c": 39295.0
        },
        {
          "ts": "2024-08-06T10:46:00-04:00",
          "o": 39295.0,
          "h": 39345.0,
          "l": 39294.0,
          "c": 39325.0
        },
        {
          "ts": "2024-08-06T10:47:00-04:00",
          "o": 39324.0,
          "h": 39370.0,
          "l": 39322.0,
          "c": 39363.0
        },
        {
          "ts": "2024-08-06T10:48:00-04:00",
          "o": 39364.0,
          "h": 39372.0,
          "l": 39350.0,
          "c": 39361.0
        },
        {
          "ts": "2024-08-06T10:49:00-04:00",
          "o": 39362.0,
          "h": 39396.0,
          "l": 39360.0,
          "c": 39386.0
        },
        {
          "ts": "2024-08-06T10:50:00-04:00",
          "o": 39385.0,
          "h": 39386.0,
          "l": 39324.0,
          "c": 39341.0
        },
        {
          "ts": "2024-08-06T10:51:00-04:00",
          "o": 39342.0,
          "h": 39348.0,
          "l": 39314.0,
          "c": 39346.0
        },
        {
          "ts": "2024-08-06T10:52:00-04:00",
          "o": 39350.0,
          "h": 39372.0,
          "l": 39339.0,
          "c": 39367.0
        },
        {
          "ts": "2024-08-06T10:53:00-04:00",
          "o": 39366.0,
          "h": 39389.0,
          "l": 39359.0,
          "c": 39361.0
        },
        {
          "ts": "2024-08-06T10:54:00-04:00",
          "o": 39360.0,
          "h": 39378.0,
          "l": 39348.0,
          "c": 39350.0
        },
        {
          "ts": "2024-08-06T10:55:00-04:00",
          "o": 39347.0,
          "h": 39349.0,
          "l": 39326.0,
          "c": 39339.0
        },
        {
          "ts": "2024-08-06T10:56:00-04:00",
          "o": 39339.0,
          "h": 39350.0,
          "l": 39321.0,
          "c": 39334.0
        },
        {
          "ts": "2024-08-06T10:57:00-04:00",
          "o": 39333.0,
          "h": 39339.0,
          "l": 39296.0,
          "c": 39312.0
        },
        {
          "ts": "2024-08-06T10:58:00-04:00",
          "o": 39311.0,
          "h": 39321.0,
          "l": 39288.0,
          "c": 39297.0
        },
        {
          "ts": "2024-08-06T10:59:00-04:00",
          "o": 39296.0,
          "h": 39324.0,
          "l": 39291.0,
          "c": 39317.0
        }
      ]
    },
    {
      "date": "2023-03-13",
      "side": "long",
      "level": "PDL",
      "level_price": 31787.0,
      "entry_ts": "2023-03-13T10:00:00-04:00",
      "entry_price": 32004.0,
      "sl_price": 31608.0,
      "tp1R_price": 32400.0,
      "pnl_pts": 113.0,
      "outcome": "win",
      "manip_window": {
        "start_ts": "2023-03-13T09:30:00-04:00",
        "end_ts": "2023-03-13T09:59:00-04:00"
      },
      "trade_window": {
        "start_ts": "2023-03-13T10:00:00-04:00",
        "end_ts": "2023-03-13T10:59:00-04:00"
      },
      "bars": [
        {
          "ts": "2023-03-13T09:25:00-04:00",
          "o": 31724.0,
          "h": 31724.0,
          "l": 31700.0,
          "c": 31703.0
        },
        {
          "ts": "2023-03-13T09:26:00-04:00",
          "o": 31704.0,
          "h": 31705.0,
          "l": 31669.0,
          "c": 31669.0
        },
        {
          "ts": "2023-03-13T09:27:00-04:00",
          "o": 31669.0,
          "h": 31679.0,
          "l": 31655.0,
          "c": 31668.0
        },
        {
          "ts": "2023-03-13T09:28:00-04:00",
          "o": 31669.0,
          "h": 31669.0,
          "l": 31618.0,
          "c": 31623.0
        },
        {
          "ts": "2023-03-13T09:29:00-04:00",
          "o": 31620.0,
          "h": 31627.0,
          "l": 31593.0,
          "c": 31624.0
        },
        {
          "ts": "2023-03-13T09:30:00-04:00",
          "o": 31621.0,
          "h": 31730.0,
          "l": 31608.0,
          "c": 31709.0
        },
        {
          "ts": "2023-03-13T09:31:00-04:00",
          "o": 31708.0,
          "h": 31726.0,
          "l": 31634.0,
          "c": 31723.0
        },
        {
          "ts": "2023-03-13T09:32:00-04:00",
          "o": 31723.0,
          "h": 31754.0,
          "l": 31701.0,
          "c": 31745.0
        },
        {
          "ts": "2023-03-13T09:33:00-04:00",
          "o": 31748.0,
          "h": 31786.0,
          "l": 31705.0,
          "c": 31753.0
        },
        {
          "ts": "2023-03-13T09:34:00-04:00",
          "o": 31752.0,
          "h": 31756.0,
          "l": 31709.0,
          "c": 31715.0
        },
        {
          "ts": "2023-03-13T09:35:00-04:00",
          "o": 31716.0,
          "h": 31737.0,
          "l": 31693.0,
          "c": 31717.0
        },
        {
          "ts": "2023-03-13T09:36:00-04:00",
          "o": 31722.0,
          "h": 31774.0,
          "l": 31713.0,
          "c": 31749.0
        },
        {
          "ts": "2023-03-13T09:37:00-04:00",
          "o": 31749.0,
          "h": 31768.0,
          "l": 31726.0,
          "c": 31757.0
        },
        {
          "ts": "2023-03-13T09:38:00-04:00",
          "o": 31756.0,
          "h": 31788.0,
          "l": 31728.0,
          "c": 31770.0
        },
        {
          "ts": "2023-03-13T09:39:00-04:00",
          "o": 31777.0,
          "h": 31806.0,
          "l": 31755.0,
          "c": 31801.0
        },
        {
          "ts": "2023-03-13T09:40:00-04:00",
          "o": 31803.0,
          "h": 31818.0,
          "l": 31759.0,
          "c": 31786.0
        },
        {
          "ts": "2023-03-13T09:41:00-04:00",
          "o": 31780.0,
          "h": 31780.0,
          "l": 31724.0,
          "c": 31746.0
        },
        {
          "ts": "2023-03-13T09:42:00-04:00",
          "o": 31742.0,
          "h": 31768.0,
          "l": 31722.0,
          "c": 31768.0
        },
        {
          "ts": "2023-03-13T09:43:00-04:00",
          "o": 31770.0,
          "h": 31782.0,
          "l": 31737.0,
          "c": 31752.0
        },
        {
          "ts": "2023-03-13T09:44:00-04:00",
          "o": 31753.0,
          "h": 31775.0,
          "l": 31729.0,
          "c": 31768.0
        },
        {
          "ts": "2023-03-13T09:45:00-04:00",
          "o": 31770.0,
          "h": 31803.0,
          "l": 31749.0,
          "c": 31796.0
        },
        {
          "ts": "2023-03-13T09:46:00-04:00",
          "o": 31795.0,
          "h": 31795.0,
          "l": 31753.0,
          "c": 31781.0
        },
        {
          "ts": "2023-03-13T09:47:00-04:00",
          "o": 31782.0,
          "h": 31875.0,
          "l": 31771.0,
          "c": 31872.0
        },
        {
          "ts": "2023-03-13T09:48:00-04:00",
          "o": 31869.0,
          "h": 31927.0,
          "l": 31848.0,
          "c": 31913.0
        },
        {
          "ts": "2023-03-13T09:49:00-04:00",
          "o": 31916.0,
          "h": 31944.0,
          "l": 31907.0,
          "c": 31912.0
        },
        {
          "ts": "2023-03-13T09:50:00-04:00",
          "o": 31911.0,
          "h": 31998.0,
          "l": 31905.0,
          "c": 31985.0
        },
        {
          "ts": "2023-03-13T09:51:00-04:00",
          "o": 31982.0,
          "h": 32005.0,
          "l": 31957.0,
          "c": 31986.0
        },
        {
          "ts": "2023-03-13T09:52:00-04:00",
          "o": 31988.0,
          "h": 31997.0,
          "l": 31953.0,
          "c": 31960.0
        },
        {
          "ts": "2023-03-13T09:53:00-04:00",
          "o": 31962.0,
          "h": 31963.0,
          "l": 31874.0,
          "c": 31891.0
        },
        {
          "ts": "2023-03-13T09:54:00-04:00",
          "o": 31892.0,
          "h": 31962.0,
          "l": 31887.0,
          "c": 31951.0
        },
        {
          "ts": "2023-03-13T09:55:00-04:00",
          "o": 31951.0,
          "h": 31982.0,
          "l": 31912.0,
          "c": 31958.0
        },
        {
          "ts": "2023-03-13T09:56:00-04:00",
          "o": 31956.0,
          "h": 31986.0,
          "l": 31935.0,
          "c": 31981.0
        },
        {
          "ts": "2023-03-13T09:57:00-04:00",
          "o": 31981.0,
          "h": 32014.0,
          "l": 31971.0,
          "c": 31991.0
        },
        {
          "ts": "2023-03-13T09:58:00-04:00",
          "o": 31991.0,
          "h": 32047.0,
          "l": 31991.0,
          "c": 32029.0
        },
        {
          "ts": "2023-03-13T09:59:00-04:00",
          "o": 32021.0,
          "h": 32039.0,
          "l": 31993.0,
          "c": 32005.0
        },
        {
          "ts": "2023-03-13T10:00:00-04:00",
          "o": 32004.0,
          "h": 32010.0,
          "l": 31961.0,
          "c": 31980.0
        },
        {
          "ts": "2023-03-13T10:01:00-04:00",
          "o": 31976.0,
          "h": 32011.0,
          "l": 31950.0,
          "c": 31965.0
        },
        {
          "ts": "2023-03-13T10:02:00-04:00",
          "o": 31963.0,
          "h": 32017.0,
          "l": 31961.0,
          "c": 31974.0
        },
        {
          "ts": "2023-03-13T10:03:00-04:00",
          "o": 31969.0,
          "h": 32064.0,
          "l": 31968.0,
          "c": 32050.0
        },
        {
          "ts": "2023-03-13T10:04:00-04:00",
          "o": 32049.0,
          "h": 32070.0,
          "l": 32028.0,
          "c": 32034.0
        },
        {
          "ts": "2023-03-13T10:05:00-04:00",
          "o": 32033.0,
          "h": 32049.0,
          "l": 32005.0,
          "c": 32006.0
        },
        {
          "ts": "2023-03-13T10:06:00-04:00",
          "o": 32004.0,
          "h": 32027.0,
          "l": 31989.0,
          "c": 32014.0
        },
        {
          "ts": "2023-03-13T10:07:00-04:00",
          "o": 32017.0,
          "h": 32070.0,
          "l": 31946.0,
          "c": 32068.0
        },
        {
          "ts": "2023-03-13T10:08:00-04:00",
          "o": 32069.0,
          "h": 32134.0,
          "l": 32058.0,
          "c": 32090.0
        },
        {
          "ts": "2023-03-13T10:09:00-04:00",
          "o": 32093.0,
          "h": 32093.0,
          "l": 32029.0,
          "c": 32051.0
        },
        {
          "ts": "2023-03-13T10:10:00-04:00",
          "o": 32050.0,
          "h": 32072.0,
          "l": 32039.0,
          "c": 32051.0
        },
        {
          "ts": "2023-03-13T10:11:00-04:00",
          "o": 32039.0,
          "h": 32039.0,
          "l": 31982.0,
          "c": 32001.0
        },
        {
          "ts": "2023-03-13T10:12:00-04:00",
          "o": 32004.0,
          "h": 32016.0,
          "l": 31928.0,
          "c": 31952.0
        },
        {
          "ts": "2023-03-13T10:13:00-04:00",
          "o": 31951.0,
          "h": 31956.0,
          "l": 31915.0,
          "c": 31951.0
        },
        {
          "ts": "2023-03-13T10:14:00-04:00",
          "o": 31953.0,
          "h": 31966.0,
          "l": 31935.0,
          "c": 31950.0
        },
        {
          "ts": "2023-03-13T10:15:00-04:00",
          "o": 31952.0,
          "h": 31952.0,
          "l": 31899.0,
          "c": 31906.0
        },
        {
          "ts": "2023-03-13T10:16:00-04:00",
          "o": 31911.0,
          "h": 31933.0,
          "l": 31869.0,
          "c": 31885.0
        },
        {
          "ts": "2023-03-13T10:17:00-04:00",
          "o": 31889.0,
          "h": 31900.0,
          "l": 31862.0,
          "c": 31883.0
        },
        {
          "ts": "2023-03-13T10:18:00-04:00",
          "o": 31877.0,
          "h": 31934.0,
          "l": 31872.0,
          "c": 31898.0
        },
        {
          "ts": "2023-03-13T10:19:00-04:00",
          "o": 31899.0,
          "h": 31899.0,
          "l": 31849.0,
          "c": 31860.0
        },
        {
          "ts": "2023-03-13T10:20:00-04:00",
          "o": 31858.0,
          "h": 31872.0,
          "l": 31827.0,
          "c": 31872.0
        },
        {
          "ts": "2023-03-13T10:21:00-04:00",
          "o": 31872.0,
          "h": 31911.0,
          "l": 31840.0,
          "c": 31843.0
        },
        {
          "ts": "2023-03-13T10:22:00-04:00",
          "o": 31842.0,
          "h": 31927.0,
          "l": 31840.0,
          "c": 31894.0
        },
        {
          "ts": "2023-03-13T10:23:00-04:00",
          "o": 31893.0,
          "h": 31903.0,
          "l": 31836.0,
          "c": 31838.0
        },
        {
          "ts": "2023-03-13T10:24:00-04:00",
          "o": 31839.0,
          "h": 31872.0,
          "l": 31830.0,
          "c": 31860.0
        },
        {
          "ts": "2023-03-13T10:25:00-04:00",
          "o": 31862.0,
          "h": 31879.0,
          "l": 31821.0,
          "c": 31828.0
        },
        {
          "ts": "2023-03-13T10:26:00-04:00",
          "o": 31827.0,
          "h": 31884.0,
          "l": 31816.0,
          "c": 31862.0
        },
        {
          "ts": "2023-03-13T10:27:00-04:00",
          "o": 31862.0,
          "h": 31881.0,
          "l": 31824.0,
          "c": 31830.0
        },
        {
          "ts": "2023-03-13T10:28:00-04:00",
          "o": 31828.0,
          "h": 31855.0,
          "l": 31826.0,
          "c": 31832.0
        },
        {
          "ts": "2023-03-13T10:29:00-04:00",
          "o": 31834.0,
          "h": 31841.0,
          "l": 31796.0,
          "c": 31824.0
        },
        {
          "ts": "2023-03-13T10:30:00-04:00",
          "o": 31825.0,
          "h": 31890.0,
          "l": 31825.0,
          "c": 31868.0
        },
        {
          "ts": "2023-03-13T10:31:00-04:00",
          "o": 31864.0,
          "h": 31878.0,
          "l": 31822.0,
          "c": 31860.0
        },
        {
          "ts": "2023-03-13T10:32:00-04:00",
          "o": 31859.0,
          "h": 31942.0,
          "l": 31849.0,
          "c": 31941.0
        },
        {
          "ts": "2023-03-13T10:33:00-04:00",
          "o": 31935.0,
          "h": 31962.0,
          "l": 31912.0,
          "c": 31946.0
        },
        {
          "ts": "2023-03-13T10:34:00-04:00",
          "o": 31946.0,
          "h": 31964.0,
          "l": 31923.0,
          "c": 31961.0
        },
        {
          "ts": "2023-03-13T10:35:00-04:00",
          "o": 31963.0,
          "h": 31991.0,
          "l": 31953.0,
          "c": 31964.0
        },
        {
          "ts": "2023-03-13T10:36:00-04:00",
          "o": 31963.0,
          "h": 31980.0,
          "l": 31925.0,
          "c": 31932.0
        },
        {
          "ts": "2023-03-13T10:37:00-04:00",
          "o": 31934.0,
          "h": 31957.0,
          "l": 31908.0,
          "c": 31948.0
        },
        {
          "ts": "2023-03-13T10:38:00-04:00",
          "o": 31946.0,
          "h": 31946.0,
          "l": 31889.0,
          "c": 31916.0
        },
        {
          "ts": "2023-03-13T10:39:00-04:00",
          "o": 31914.0,
          "h": 31967.0,
          "l": 31912.0,
          "c": 31941.0
        },
        {
          "ts": "2023-03-13T10:40:00-04:00",
          "o": 31945.0,
          "h": 31962.0,
          "l": 31928.0,
          "c": 31941.0
        },
        {
          "ts": "2023-03-13T10:41:00-04:00",
          "o": 31937.0,
          "h": 31944.0,
          "l": 31909.0,
          "c": 31912.0
        },
        {
          "ts": "2023-03-13T10:42:00-04:00",
          "o": 31912.0,
          "h": 31915.0,
          "l": 31880.0,
          "c": 31897.0
        },
        {
          "ts": "2023-03-13T10:43:00-04:00",
          "o": 31896.0,
          "h": 31941.0,
          "l": 31885.0,
          "c": 31941.0
        },
        {
          "ts": "2023-03-13T10:44:00-04:00",
          "o": 31945.0,
          "h": 31988.0,
          "l": 31945.0,
          "c": 31973.0
        },
        {
          "ts": "2023-03-13T10:45:00-04:00",
          "o": 31973.0,
          "h": 31997.0,
          "l": 31959.0,
          "c": 31995.0
        },
        {
          "ts": "2023-03-13T10:46:00-04:00",
          "o": 31994.0,
          "h": 32017.0,
          "l": 31977.0,
          "c": 31996.0
        },
        {
          "ts": "2023-03-13T10:47:00-04:00",
          "o": 31992.0,
          "h": 32028.0,
          "l": 31947.0,
          "c": 32022.0
        },
        {
          "ts": "2023-03-13T10:48:00-04:00",
          "o": 32021.0,
          "h": 32029.0,
          "l": 31994.0,
          "c": 32022.0
        },
        {
          "ts": "2023-03-13T10:49:00-04:00",
          "o": 32022.0,
          "h": 32026.0,
          "l": 31979.0,
          "c": 31997.0
        },
        {
          "ts": "2023-03-13T10:50:00-04:00",
          "o": 31997.0,
          "h": 32018.0,
          "l": 31926.0,
          "c": 31934.0
        },
        {
          "ts": "2023-03-13T10:51:00-04:00",
          "o": 31934.0,
          "h": 31959.0,
          "l": 31925.0,
          "c": 31937.0
        },
        {
          "ts": "2023-03-13T10:52:00-04:00",
          "o": 31939.0,
          "h": 31959.0,
          "l": 31869.0,
          "c": 31889.0
        },
        {
          "ts": "2023-03-13T10:53:00-04:00",
          "o": 31888.0,
          "h": 31918.0,
          "l": 31873.0,
          "c": 31909.0
        },
        {
          "ts": "2023-03-13T10:54:00-04:00",
          "o": 31910.0,
          "h": 31941.0,
          "l": 31881.0,
          "c": 31939.0
        },
        {
          "ts": "2023-03-13T10:55:00-04:00",
          "o": 31943.0,
          "h": 32058.0,
          "l": 31935.0,
          "c": 32033.0
        },
        {
          "ts": "2023-03-13T10:56:00-04:00",
          "o": 32038.0,
          "h": 32109.0,
          "l": 32028.0,
          "c": 32099.0
        },
        {
          "ts": "2023-03-13T10:57:00-04:00",
          "o": 32097.0,
          "h": 32127.0,
          "l": 32079.0,
          "c": 32099.0
        },
        {
          "ts": "2023-03-13T10:58:00-04:00",
          "o": 32093.0,
          "h": 32126.0,
          "l": 32093.0,
          "c": 32115.0
        },
        {
          "ts": "2023-03-13T10:59:00-04:00",
          "o": 32113.0,
          "h": 32123.0,
          "l": 32103.0,
          "c": 32117.0
        }
      ]
    },
    {
      "date": "2024-10-29",
      "side": "long",
      "level": "AsiaLo",
      "level_price": 42515.0,
      "entry_ts": "2024-10-29T10:00:00-04:00",
      "entry_price": 42504.0,
      "sl_price": 42364.0,
      "tp1R_price": 42644.0,
      "pnl_pts": 91.0,
      "outcome": "win",
      "manip_window": {
        "start_ts": "2024-10-29T09:30:00-04:00",
        "end_ts": "2024-10-29T09:59:00-04:00"
      },
      "trade_window": {
        "start_ts": "2024-10-29T10:00:00-04:00",
        "end_ts": "2024-10-29T10:59:00-04:00"
      },
      "bars": [
        {
          "ts": "2024-10-29T09:25:00-04:00",
          "o": 42430.0,
          "h": 42436.0,
          "l": 42426.0,
          "c": 42432.0
        },
        {
          "ts": "2024-10-29T09:26:00-04:00",
          "o": 42431.0,
          "h": 42432.0,
          "l": 42417.0,
          "c": 42417.0
        },
        {
          "ts": "2024-10-29T09:27:00-04:00",
          "o": 42417.0,
          "h": 42420.0,
          "l": 42409.0,
          "c": 42410.0
        },
        {
          "ts": "2024-10-29T09:28:00-04:00",
          "o": 42412.0,
          "h": 42436.0,
          "l": 42410.0,
          "c": 42436.0
        },
        {
          "ts": "2024-10-29T09:29:00-04:00",
          "o": 42434.0,
          "h": 42437.0,
          "l": 42410.0,
          "c": 42415.0
        },
        {
          "ts": "2024-10-29T09:30:00-04:00",
          "o": 42413.0,
          "h": 42428.0,
          "l": 42389.0,
          "c": 42406.0
        },
        {
          "ts": "2024-10-29T09:31:00-04:00",
          "o": 42408.0,
          "h": 42412.0,
          "l": 42364.0,
          "c": 42377.0
        },
        {
          "ts": "2024-10-29T09:32:00-04:00",
          "o": 42375.0,
          "h": 42459.0,
          "l": 42369.0,
          "c": 42455.0
        },
        {
          "ts": "2024-10-29T09:33:00-04:00",
          "o": 42454.0,
          "h": 42470.0,
          "l": 42422.0,
          "c": 42423.0
        },
        {
          "ts": "2024-10-29T09:34:00-04:00",
          "o": 42423.0,
          "h": 42433.0,
          "l": 42408.0,
          "c": 42432.0
        },
        {
          "ts": "2024-10-29T09:35:00-04:00",
          "o": 42433.0,
          "h": 42433.0,
          "l": 42397.0,
          "c": 42414.0
        },
        {
          "ts": "2024-10-29T09:36:00-04:00",
          "o": 42415.0,
          "h": 42424.0,
          "l": 42399.0,
          "c": 42417.0
        },
        {
          "ts": "2024-10-29T09:37:00-04:00",
          "o": 42414.0,
          "h": 42425.0,
          "l": 42403.0,
          "c": 42408.0
        },
        {
          "ts": "2024-10-29T09:38:00-04:00",
          "o": 42407.0,
          "h": 42407.0,
          "l": 42381.0,
          "c": 42391.0
        },
        {
          "ts": "2024-10-29T09:39:00-04:00",
          "o": 42392.0,
          "h": 42400.0,
          "l": 42376.0,
          "c": 42394.0
        },
        {
          "ts": "2024-10-29T09:40:00-04:00",
          "o": 42394.0,
          "h": 42412.0,
          "l": 42388.0,
          "c": 42412.0
        },
        {
          "ts": "2024-10-29T09:41:00-04:00",
          "o": 42412.0,
          "h": 42418.0,
          "l": 42398.0,
          "c": 42403.0
        },
        {
          "ts": "2024-10-29T09:42:00-04:00",
          "o": 42402.0,
          "h": 42425.0,
          "l": 42392.0,
          "c": 42413.0
        },
        {
          "ts": "2024-10-29T09:43:00-04:00",
          "o": 42411.0,
          "h": 42427.0,
          "l": 42400.0,
          "c": 42423.0
        },
        {
          "ts": "2024-10-29T09:44:00-04:00",
          "o": 42422.0,
          "h": 42427.0,
          "l": 42412.0,
          "c": 42418.0
        },
        {
          "ts": "2024-10-29T09:45:00-04:00",
          "o": 42419.0,
          "h": 42448.0,
          "l": 42398.0,
          "c": 42446.0
        },
        {
          "ts": "2024-10-29T09:46:00-04:00",
          "o": 42445.0,
          "h": 42445.0,
          "l": 42416.0,
          "c": 42424.0
        },
        {
          "ts": "2024-10-29T09:47:00-04:00",
          "o": 42425.0,
          "h": 42457.0,
          "l": 42424.0,
          "c": 42456.0
        },
        {
          "ts": "2024-10-29T09:48:00-04:00",
          "o": 42456.0,
          "h": 42464.0,
          "l": 42449.0,
          "c": 42457.0
        },
        {
          "ts": "2024-10-29T09:49:00-04:00",
          "o": 42455.0,
          "h": 42458.0,
          "l": 42436.0,
          "c": 42440.0
        },
        {
          "ts": "2024-10-29T09:50:00-04:00",
          "o": 42440.0,
          "h": 42480.0,
          "l": 42440.0,
          "c": 42477.0
        },
        {
          "ts": "2024-10-29T09:51:00-04:00",
          "o": 42478.0,
          "h": 42486.0,
          "l": 42454.0,
          "c": 42458.0
        },
        {
          "ts": "2024-10-29T09:52:00-04:00",
          "o": 42460.0,
          "h": 42470.0,
          "l": 42447.0,
          "c": 42457.0
        },
        {
          "ts": "2024-10-29T09:53:00-04:00",
          "o": 42457.0,
          "h": 42486.0,
          "l": 42456.0,
          "c": 42486.0
        },
        {
          "ts": "2024-10-29T09:54:00-04:00",
          "o": 42484.0,
          "h": 42508.0,
          "l": 42482.0,
          "c": 42508.0
        },
        {
          "ts": "2024-10-29T09:55:00-04:00",
          "o": 42505.0,
          "h": 42536.0,
          "l": 42504.0,
          "c": 42526.0
        },
        {
          "ts": "2024-10-29T09:56:00-04:00",
          "o": 42525.0,
          "h": 42535.0,
          "l": 42504.0,
          "c": 42506.0
        },
        {
          "ts": "2024-10-29T09:57:00-04:00",
          "o": 42506.0,
          "h": 42506.0,
          "l": 42491.0,
          "c": 42494.0
        },
        {
          "ts": "2024-10-29T09:58:00-04:00",
          "o": 42494.0,
          "h": 42498.0,
          "l": 42483.0,
          "c": 42493.0
        },
        {
          "ts": "2024-10-29T09:59:00-04:00",
          "o": 42493.0,
          "h": 42518.0,
          "l": 42492.0,
          "c": 42518.0
        },
        {
          "ts": "2024-10-29T10:00:00-04:00",
          "o": 42504.0,
          "h": 42542.0,
          "l": 42473.0,
          "c": 42484.0
        },
        {
          "ts": "2024-10-29T10:01:00-04:00",
          "o": 42485.0,
          "h": 42515.0,
          "l": 42474.0,
          "c": 42511.0
        },
        {
          "ts": "2024-10-29T10:02:00-04:00",
          "o": 42514.0,
          "h": 42541.0,
          "l": 42514.0,
          "c": 42529.0
        },
        {
          "ts": "2024-10-29T10:03:00-04:00",
          "o": 42529.0,
          "h": 42559.0,
          "l": 42524.0,
          "c": 42556.0
        },
        {
          "ts": "2024-10-29T10:04:00-04:00",
          "o": 42556.0,
          "h": 42569.0,
          "l": 42546.0,
          "c": 42553.0
        },
        {
          "ts": "2024-10-29T10:05:00-04:00",
          "o": 42557.0,
          "h": 42567.0,
          "l": 42537.0,
          "c": 42566.0
        },
        {
          "ts": "2024-10-29T10:06:00-04:00",
          "o": 42567.0,
          "h": 42574.0,
          "l": 42559.0,
          "c": 42568.0
        },
        {
          "ts": "2024-10-29T10:07:00-04:00",
          "o": 42569.0,
          "h": 42581.0,
          "l": 42553.0,
          "c": 42562.0
        },
        {
          "ts": "2024-10-29T10:08:00-04:00",
          "o": 42562.0,
          "h": 42567.0,
          "l": 42556.0,
          "c": 42566.0
        },
        {
          "ts": "2024-10-29T10:09:00-04:00",
          "o": 42568.0,
          "h": 42585.0,
          "l": 42564.0,
          "c": 42579.0
        },
        {
          "ts": "2024-10-29T10:10:00-04:00",
          "o": 42580.0,
          "h": 42596.0,
          "l": 42575.0,
          "c": 42590.0
        },
        {
          "ts": "2024-10-29T10:11:00-04:00",
          "o": 42593.0,
          "h": 42609.0,
          "l": 42587.0,
          "c": 42607.0
        },
        {
          "ts": "2024-10-29T10:12:00-04:00",
          "o": 42606.0,
          "h": 42614.0,
          "l": 42578.0,
          "c": 42579.0
        },
        {
          "ts": "2024-10-29T10:13:00-04:00",
          "o": 42580.0,
          "h": 42590.0,
          "l": 42566.0,
          "c": 42589.0
        },
        {
          "ts": "2024-10-29T10:14:00-04:00",
          "o": 42589.0,
          "h": 42590.0,
          "l": 42563.0,
          "c": 42566.0
        },
        {
          "ts": "2024-10-29T10:15:00-04:00",
          "o": 42565.0,
          "h": 42605.0,
          "l": 42565.0,
          "c": 42605.0
        },
        {
          "ts": "2024-10-29T10:16:00-04:00",
          "o": 42603.0,
          "h": 42610.0,
          "l": 42594.0,
          "c": 42601.0
        },
        {
          "ts": "2024-10-29T10:17:00-04:00",
          "o": 42601.0,
          "h": 42608.0,
          "l": 42595.0,
          "c": 42598.0
        },
        {
          "ts": "2024-10-29T10:18:00-04:00",
          "o": 42600.0,
          "h": 42608.0,
          "l": 42597.0,
          "c": 42606.0
        },
        {
          "ts": "2024-10-29T10:19:00-04:00",
          "o": 42605.0,
          "h": 42613.0,
          "l": 42600.0,
          "c": 42601.0
        },
        {
          "ts": "2024-10-29T10:20:00-04:00",
          "o": 42600.0,
          "h": 42600.0,
          "l": 42578.0,
          "c": 42594.0
        },
        {
          "ts": "2024-10-29T10:21:00-04:00",
          "o": 42595.0,
          "h": 42603.0,
          "l": 42585.0,
          "c": 42596.0
        },
        {
          "ts": "2024-10-29T10:22:00-04:00",
          "o": 42595.0,
          "h": 42633.0,
          "l": 42592.0,
          "c": 42631.0
        },
        {
          "ts": "2024-10-29T10:23:00-04:00",
          "o": 42631.0,
          "h": 42659.0,
          "l": 42625.0,
          "c": 42658.0
        },
        {
          "ts": "2024-10-29T10:24:00-04:00",
          "o": 42658.0,
          "h": 42690.0,
          "l": 42656.0,
          "c": 42685.0
        },
        {
          "ts": "2024-10-29T10:25:00-04:00",
          "o": 42685.0,
          "h": 42687.0,
          "l": 42673.0,
          "c": 42682.0
        },
        {
          "ts": "2024-10-29T10:26:00-04:00",
          "o": 42682.0,
          "h": 42697.0,
          "l": 42670.0,
          "c": 42670.0
        },
        {
          "ts": "2024-10-29T10:27:00-04:00",
          "o": 42671.0,
          "h": 42671.0,
          "l": 42614.0,
          "c": 42618.0
        },
        {
          "ts": "2024-10-29T10:28:00-04:00",
          "o": 42617.0,
          "h": 42618.0,
          "l": 42587.0,
          "c": 42593.0
        },
        {
          "ts": "2024-10-29T10:29:00-04:00",
          "o": 42594.0,
          "h": 42610.0,
          "l": 42584.0,
          "c": 42596.0
        },
        {
          "ts": "2024-10-29T10:30:00-04:00",
          "o": 42594.0,
          "h": 42602.0,
          "l": 42580.0,
          "c": 42580.0
        },
        {
          "ts": "2024-10-29T10:31:00-04:00",
          "o": 42580.0,
          "h": 42581.0,
          "l": 42568.0,
          "c": 42577.0
        },
        {
          "ts": "2024-10-29T10:32:00-04:00",
          "o": 42580.0,
          "h": 42606.0,
          "l": 42580.0,
          "c": 42598.0
        },
        {
          "ts": "2024-10-29T10:33:00-04:00",
          "o": 42599.0,
          "h": 42601.0,
          "l": 42589.0,
          "c": 42593.0
        },
        {
          "ts": "2024-10-29T10:34:00-04:00",
          "o": 42593.0,
          "h": 42612.0,
          "l": 42593.0,
          "c": 42605.0
        },
        {
          "ts": "2024-10-29T10:35:00-04:00",
          "o": 42606.0,
          "h": 42613.0,
          "l": 42588.0,
          "c": 42590.0
        },
        {
          "ts": "2024-10-29T10:36:00-04:00",
          "o": 42591.0,
          "h": 42604.0,
          "l": 42578.0,
          "c": 42593.0
        },
        {
          "ts": "2024-10-29T10:37:00-04:00",
          "o": 42591.0,
          "h": 42610.0,
          "l": 42588.0,
          "c": 42608.0
        },
        {
          "ts": "2024-10-29T10:38:00-04:00",
          "o": 42608.0,
          "h": 42627.0,
          "l": 42604.0,
          "c": 42619.0
        },
        {
          "ts": "2024-10-29T10:39:00-04:00",
          "o": 42619.0,
          "h": 42629.0,
          "l": 42607.0,
          "c": 42627.0
        },
        {
          "ts": "2024-10-29T10:40:00-04:00",
          "o": 42626.0,
          "h": 42626.0,
          "l": 42602.0,
          "c": 42603.0
        },
        {
          "ts": "2024-10-29T10:41:00-04:00",
          "o": 42604.0,
          "h": 42631.0,
          "l": 42602.0,
          "c": 42631.0
        },
        {
          "ts": "2024-10-29T10:42:00-04:00",
          "o": 42630.0,
          "h": 42635.0,
          "l": 42612.0,
          "c": 42625.0
        },
        {
          "ts": "2024-10-29T10:43:00-04:00",
          "o": 42628.0,
          "h": 42634.0,
          "l": 42621.0,
          "c": 42624.0
        },
        {
          "ts": "2024-10-29T10:44:00-04:00",
          "o": 42624.0,
          "h": 42630.0,
          "l": 42617.0,
          "c": 42628.0
        },
        {
          "ts": "2024-10-29T10:45:00-04:00",
          "o": 42629.0,
          "h": 42632.0,
          "l": 42615.0,
          "c": 42622.0
        },
        {
          "ts": "2024-10-29T10:46:00-04:00",
          "o": 42621.0,
          "h": 42625.0,
          "l": 42604.0,
          "c": 42606.0
        },
        {
          "ts": "2024-10-29T10:47:00-04:00",
          "o": 42602.0,
          "h": 42603.0,
          "l": 42584.0,
          "c": 42600.0
        },
        {
          "ts": "2024-10-29T10:48:00-04:00",
          "o": 42601.0,
          "h": 42606.0,
          "l": 42580.0,
          "c": 42580.0
        },
        {
          "ts": "2024-10-29T10:49:00-04:00",
          "o": 42580.0,
          "h": 42608.0,
          "l": 42580.0,
          "c": 42607.0
        },
        {
          "ts": "2024-10-29T10:50:00-04:00",
          "o": 42610.0,
          "h": 42612.0,
          "l": 42595.0,
          "c": 42605.0
        },
        {
          "ts": "2024-10-29T10:51:00-04:00",
          "o": 42606.0,
          "h": 42612.0,
          "l": 42603.0,
          "c": 42610.0
        },
        {
          "ts": "2024-10-29T10:52:00-04:00",
          "o": 42610.0,
          "h": 42615.0,
          "l": 42603.0,
          "c": 42611.0
        },
        {
          "ts": "2024-10-29T10:53:00-04:00",
          "o": 42608.0,
          "h": 42610.0,
          "l": 42598.0,
          "c": 42604.0
        },
        {
          "ts": "2024-10-29T10:54:00-04:00",
          "o": 42605.0,
          "h": 42608.0,
          "l": 42594.0,
          "c": 42600.0
        },
        {
          "ts": "2024-10-29T10:55:00-04:00",
          "o": 42598.0,
          "h": 42603.0,
          "l": 42586.0,
          "c": 42600.0
        },
        {
          "ts": "2024-10-29T10:56:00-04:00",
          "o": 42600.0,
          "h": 42603.0,
          "l": 42580.0,
          "c": 42597.0
        },
        {
          "ts": "2024-10-29T10:57:00-04:00",
          "o": 42597.0,
          "h": 42613.0,
          "l": 42595.0,
          "c": 42611.0
        },
        {
          "ts": "2024-10-29T10:58:00-04:00",
          "o": 42610.0,
          "h": 42613.0,
          "l": 42601.0,
          "c": 42603.0
        },
        {
          "ts": "2024-10-29T10:59:00-04:00",
          "o": 42604.0,
          "h": 42605.0,
          "l": 42592.0,
          "c": 42595.0
        }
      ]
    }
  ]
}